{
  "metadata": {
    "run_id": "sprint1_008_h4h02_sl_pct5_squeeze_pct25_time_limit20_tp_pct8_vol_mult2.0_9a606d9",
    "config_id": "sprint1_008_h4h02_sl_pct5_squeeze_pct25_time_limit20_tp_pct8_vol_mult2.0",
    "hypothesis_id": "H4H-02",
    "hypothesis_name": "BB Squeeze Breakout",
    "category": "volatility",
    "exit_template": "trend",
    "dataset_id": "ohlcv_4h_kraken_spot_usd_526",
    "exchange": "kraken",
    "fee_bps": 26.0,
    "n_coins": 487,
    "elapsed_s": 0.14,
    "timestamp": "2026-02-17T17:00:56.480927+00:00",
    "git_hash": "9a606d9",
    "engine": "sprint1.engine (Stage 0 prefilter)"
  },
  "summary": {
    "trades": 264,
    "wr": 31.82,
    "pnl": -1865.73,
    "final_equity": 134.27,
    "pf": 0.5604,
    "dd": 93.91,
    "broke": false
  },
  "exit_classes": {
    "A": {
      "PROFIT TARGET": {
        "count": 69,
        "pnl": 1571.2089875771512,
        "wins": 69
      }
    },
    "B": {
      "TIME MAX": {
        "count": 45,
        "pnl": -128.54245480325596,
        "wins": 13
      },
      "FIXED STOP": {
        "count": 147,
        "pnl": -2746.8420674679287,
        "wins": 0
      },
      "END": {
        "count": 3,
        "pnl": 0.6110084434504804,
        "wins": 2
      }
    }
  },
  "trade_count": 264,
  "trades": [
    {
      "pair": "JTO/USD",
      "entry": 1.139,
      "exit": 1.1026,
      "pnl": -24.7223,
      "pnl_pct": -3.7084,
      "reason": "TIME MAX",
      "bars": 20,
      "entry_bar": 50,
      "exit_bar": 70,
      "size": 666.6667,
      "equity_after": 641.9443
    },
    {
      "pair": "LCAP/USD",
      "entry": 11.223,
      "exit": 11.473,
      "pnl": 11.3452,
      "pnl_pct": 1.7018,
      "reason": "TIME MAX",
      "bars": 20,
      "entry_bar": 50,
      "exit_bar": 70,
      "size": 666.6667,
      "equity_after": 1319.9562
    },
    {
      "pair": "ORCA/USD",
      "entry": 1.487,
      "exit": 1.503,
      "pnl": 3.688,
      "pnl_pct": 0.5532,
      "reason": "TIME MAX",
      "bars": 20,
      "entry_bar": 50,
      "exit_bar": 70,
      "size": 666.6667,
      "equity_after": 1990.3108
    },
    {
      "pair": "PLAY/USD",
      "entry": 0.0287,
      "exit": 0.0273,
      "pnl": -36.5355,
      "pnl_pct": -5.507,
      "reason": "FIXED STOP",
      "bars": 4,
      "entry_bar": 70,
      "exit_bar": 74,
      "size": 663.4369,
      "equity_after": 626.9015
    },
    {
      "pair": "TAKE/USD",
      "entry": 0.3163,
      "exit": 0.3005,
      "pnl": -36.5355,
      "pnl_pct": -5.507,
      "reason": "FIXED STOP",
      "bars": 5,
      "entry_bar": 70,
      "exit_bar": 75,
      "size": 663.4369,
      "equity_after": 626.9015
    },
    {
      "pair": "ANLOG/USD",
      "entry": 0.0013,
      "exit": 0.0014,
      "pnl": 46.7618,
      "pnl_pct": 7.4592,
      "reason": "PROFIT TARGET",
      "bars": 5,
      "entry_bar": 74,
      "exit_bar": 79,
      "size": 626.9015,
      "equity_after": 673.6633
    },
    {
      "pair": "CCD/USD",
      "entry": 0.0251,
      "exit": 0.0239,
      "pnl": -37.0986,
      "pnl_pct": -5.507,
      "reason": "FIXED STOP",
      "bars": 1,
      "entry_bar": 79,
      "exit_bar": 80,
      "size": 673.6633,
      "equity_after": 636.5647
    },
    {
      "pair": "QTUM/USD",
      "entry": 2.02,
      "exit": 1.919,
      "pnl": -36.5355,
      "pnl_pct": -5.507,
      "reason": "FIXED STOP",
      "bars": 12,
      "entry_bar": 70,
      "exit_bar": 82,
      "size": 663.4369,
      "equity_after": 626.9015
    },
    {
      "pair": "FORTH/USD",
      "entry": 2.36,
      "exit": 2.242,
      "pnl": -35.0556,
      "pnl_pct": -5.507,
      "reason": "FIXED STOP",
      "bars": 3,
      "entry_bar": 81,
      "exit_bar": 84,
      "size": 636.5647,
      "equity_after": 601.509
    },
    {
      "pair": "EAT/USD",
      "entry": 0.0636,
      "exit": 0.0604,
      "pnl": -33.1251,
      "pnl_pct": -5.507,
      "reason": "FIXED STOP",
      "bars": 1,
      "entry_bar": 84,
      "exit_bar": 85,
      "size": 601.509,
      "equity_after": 568.3839
    },
    {
      "pair": "RVV/USD",
      "entry": 0.0041,
      "exit": 0.0039,
      "pnl": -34.5235,
      "pnl_pct": -5.507,
      "reason": "FIXED STOP",
      "bars": 7,
      "entry_bar": 82,
      "exit_bar": 89,
      "size": 626.9015,
      "equity_after": 592.378
    },
    {
      "pair": "MET/USD",
      "entry": 0.4508,
      "exit": 0.4283,
      "pnl": -32.6223,
      "pnl_pct": -5.507,
      "reason": "FIXED STOP",
      "bars": 2,
      "entry_bar": 89,
      "exit_bar": 91,
      "size": 592.378,
      "equity_after": 559.7557
    },
    {
      "pair": "JST/USD",
      "entry": 0.034,
      "exit": 0.0347,
      "pnl": 8.6938,
      "pnl_pct": 1.3868,
      "reason": "TIME MAX",
      "bars": 20,
      "entry_bar": 75,
      "exit_bar": 95,
      "size": 626.9015,
      "equity_after": 635.5953
    },
    {
      "pair": "HNT/USD",
      "entry": 2.5063,
      "exit": 2.381,
      "pnl": -30.8257,
      "pnl_pct": -5.507,
      "reason": "FIXED STOP",
      "bars": 7,
      "entry_bar": 91,
      "exit_bar": 98,
      "size": 559.7557,
      "equity_after": 528.93
    },
    {
      "pair": "BKS/USD",
      "entry": 0.0075,
      "exit": 0.0073,
      "pnl": -21.0966,
      "pnl_pct": -3.7117,
      "reason": "TIME MAX",
      "bars": 20,
      "entry_bar": 85,
      "exit_bar": 105,
      "size": 568.3839,
      "equity_after": 547.2873
    },
    {
      "pair": "OXT/USD",
      "entry": 0.0391,
      "exit": 0.0372,
      "pnl": -35.0022,
      "pnl_pct": -5.507,
      "reason": "FIXED STOP",
      "bars": 11,
      "entry_bar": 95,
      "exit_bar": 106,
      "size": 635.5953,
      "equity_after": 600.5931
    },
    {
      "pair": "ANLOG/USD",
      "entry": 0.0014,
      "exit": 0.0013,
      "pnl": -33.0747,
      "pnl_pct": -5.507,
      "reason": "FIXED STOP",
      "bars": 3,
      "entry_bar": 106,
      "exit_bar": 109,
      "size": 600.5931,
      "equity_after": 567.5184
    },
    {
      "pair": "GAME2/USD",
      "entry": 0.0018,
      "exit": 0.0017,
      "pnl": -30.1391,
      "pnl_pct": -5.507,
      "reason": "FIXED STOP",
      "bars": 5,
      "entry_bar": 105,
      "exit_bar": 110,
      "size": 547.2873,
      "equity_after": 517.1482
    },
    {
      "pair": "MF/USD",
      "entry": 0.0248,
      "exit": 0.0268,
      "pnl": 42.3323,
      "pnl_pct": 7.4592,
      "reason": "PROFIT TARGET",
      "bars": 1,
      "entry_bar": 109,
      "exit_bar": 110,
      "size": 567.5184,
      "equity_after": 1126.999
    },
    {
      "pair": "SYND/USD",
      "entry": 0.1378,
      "exit": 0.1488,
      "pnl": 42.0326,
      "pnl_pct": 7.4592,
      "reason": "PROFIT TARGET",
      "bars": 1,
      "entry_bar": 110,
      "exit_bar": 111,
      "size": 563.4995,
      "equity_after": 605.532
    },
    {
      "pair": "DRV/USD",
      "entry": 0.0411,
      "exit": 0.039,
      "pnl": -33.3466,
      "pnl_pct": -5.507,
      "reason": "FIXED STOP",
      "bars": 4,
      "entry_bar": 111,
      "exit_bar": 115,
      "size": 605.532,
      "equity_after": 572.1854
    },
    {
      "pair": "SAHARA/USD",
      "entry": 0.0752,
      "exit": 0.0765,
      "pnl": 6.5123,
      "pnl_pct": 1.2312,
      "reason": "TIME MAX",
      "bars": 20,
      "entry_bar": 98,
      "exit_bar": 118,
      "size": 528.93,
      "equity_after": 535.4423
    },
    {
      "pair": "IAG/USD",
      "entry": 0.1072,
      "exit": 0.1018,
      "pnl": -31.0319,
      "pnl_pct": -5.507,
      "reason": "FIXED STOP",
      "bars": 9,
      "entry_bar": 110,
      "exit_bar": 119,
      "size": 563.4995,
      "equity_after": 532.4676
    },
    {
      "pair": "AIN/USD",
      "entry": 0.0815,
      "exit": 0.0774,
      "pnl": -29.323,
      "pnl_pct": -5.507,
      "reason": "FIXED STOP",
      "bars": 1,
      "entry_bar": 119,
      "exit_bar": 120,
      "size": 532.4676,
      "equity_after": 503.1446
    },
    {
      "pair": "RIVER/USD",
      "entry": 3.53,
      "exit": 3.8124,
      "pnl": 39.9397,
      "pnl_pct": 7.4592,
      "reason": "PROFIT TARGET",
      "bars": 5,
      "entry_bar": 118,
      "exit_bar": 123,
      "size": 535.4423,
      "equity_after": 575.382
    },
    {
      "pair": "CCD/USD",
      "entry": 0.0289,
      "exit": 0.0313,
      "pnl": 42.6805,
      "pnl_pct": 7.4592,
      "reason": "PROFIT TARGET",
      "bars": 12,
      "entry_bar": 115,
      "exit_bar": 127,
      "size": 572.1854,
      "equity_after": 614.8658
    },
    {
      "pair": "HOLO/USD",
      "entry": 0.0989,
      "exit": 0.094,
      "pnl": -31.6863,
      "pnl_pct": -5.507,
      "reason": "FIXED STOP",
      "bars": 5,
      "entry_bar": 123,
      "exit_bar": 128,
      "size": 575.382,
      "equity_after": 543.6957
    },
    {
      "pair": "VELODROME/USD",
      "entry": 0.0332,
      "exit": 0.0359,
      "pnl": 40.5554,
      "pnl_pct": 7.4592,
      "reason": "PROFIT TARGET",
      "bars": 1,
      "entry_bar": 128,
      "exit_bar": 129,
      "size": 543.6957,
      "equity_after": 584.2511
    },
    {
      "pair": "ELX/USD",
      "entry": 0.0899,
      "exit": 0.0971,
      "pnl": 43.5805,
      "pnl_pct": 7.4592,
      "reason": "PROFIT TARGET",
      "bars": 3,
      "entry_bar": 129,
      "exit_bar": 132,
      "size": 584.2511,
      "equity_after": 627.8315
    },
    {
      "pair": "KMNO/USD",
      "entry": 0.0621,
      "exit": 0.059,
      "pnl": -27.7082,
      "pnl_pct": -5.507,
      "reason": "FIXED STOP",
      "bars": 19,
      "entry_bar": 120,
      "exit_bar": 139,
      "size": 503.1446,
      "equity_after": 475.4364
    },
    {
      "pair": "BSU/USD",
      "entry": 0.1484,
      "exit": 0.1469,
      "pnl": -9.7254,
      "pnl_pct": -1.5817,
      "reason": "TIME MAX",
      "bars": 20,
      "entry_bar": 127,
      "exit_bar": 147,
      "size": 614.8658,
      "equity_after": 605.1405
    },
    {
      "pair": "VERSE/USD",
      "entry": 0.1071,
      "exit": 0.1054,
      "pnl": -13.2044,
      "pnl_pct": -2.1032,
      "reason": "TIME MAX",
      "bars": 20,
      "entry_bar": 132,
      "exit_bar": 152,
      "size": 627.8315,
      "equity_after": 614.6271
    },
    {
      "pair": "PDA/USD",
      "entry": 0.0027,
      "exit": 0.0026,
      "pnl": -33.3251,
      "pnl_pct": -5.507,
      "reason": "FIXED STOP",
      "bars": 7,
      "entry_bar": 147,
      "exit_bar": 154,
      "size": 605.1405,
      "equity_after": 571.8154
    },
    {
      "pair": "COW/USD",
      "entry": 0.2285,
      "exit": 0.2171,
      "pnl": -33.8475,
      "pnl_pct": -5.507,
      "reason": "FIXED STOP",
      "bars": 2,
      "entry_bar": 152,
      "exit_bar": 154,
      "size": 614.6271,
      "equity_after": 1152.595
    },
    {
      "pair": "CVC/USD",
      "entry": 0.0585,
      "exit": 0.0632,
      "pnl": 42.9872,
      "pnl_pct": 7.4592,
      "reason": "PROFIT TARGET",
      "bars": 1,
      "entry_bar": 154,
      "exit_bar": 155,
      "size": 576.2975,
      "equity_after": 619.2847
    },
    {
      "pair": "POWR/USD",
      "entry": 0.1092,
      "exit": 0.1179,
      "pnl": 42.9872,
      "pnl_pct": 7.4592,
      "reason": "PROFIT TARGET",
      "bars": 1,
      "entry_bar": 154,
      "exit_bar": 155,
      "size": 576.2975,
      "equity_after": 1238.5693
    },
    {
      "pair": "CTSI/USD",
      "entry": 0.0508,
      "exit": 0.0483,
      "pnl": -34.104,
      "pnl_pct": -5.507,
      "reason": "FIXED STOP",
      "bars": 1,
      "entry_bar": 155,
      "exit_bar": 156,
      "size": 619.2847,
      "equity_after": 585.1807
    },
    {
      "pair": "ANKR/USD",
      "entry": 0.0105,
      "exit": 0.0099,
      "pnl": -34.104,
      "pnl_pct": -5.507,
      "reason": "FIXED STOP",
      "bars": 3,
      "entry_bar": 155,
      "exit_bar": 158,
      "size": 619.2847,
      "equity_after": 585.1807
    },
    {
      "pair": "MXNB/USD",
      "entry": 0.054,
      "exit": 0.0546,
      "pnl": 2.0916,
      "pnl_pct": 0.4399,
      "reason": "TIME MAX",
      "bars": 20,
      "entry_bar": 139,
      "exit_bar": 159,
      "size": 475.4364,
      "equity_after": 477.528
    },
    {
      "pair": "QTUM/USD",
      "entry": 1.9407,
      "exit": 1.8437,
      "pnl": -32.2259,
      "pnl_pct": -5.507,
      "reason": "FIXED STOP",
      "bars": 3,
      "entry_bar": 156,
      "exit_bar": 159,
      "size": 585.1807,
      "equity_after": 1030.4827
    },
    {
      "pair": "TAKE/USD",
      "entry": 0.3535,
      "exit": 0.3358,
      "pnl": -28.3743,
      "pnl_pct": -5.507,
      "reason": "FIXED STOP",
      "bars": 4,
      "entry_bar": 159,
      "exit_bar": 163,
      "size": 515.2414,
      "equity_after": 486.867
    },
    {
      "pair": "PRCL/USD",
      "entry": 0.0436,
      "exit": 0.0414,
      "pnl": -28.3743,
      "pnl_pct": -5.507,
      "reason": "FIXED STOP",
      "bars": 4,
      "entry_bar": 159,
      "exit_bar": 163,
      "size": 515.2414,
      "equity_after": 973.7341
    },
    {
      "pair": "SPICE/USD",
      "entry": 0.0,
      "exit": 0.0,
      "pnl": -26.8118,
      "pnl_pct": -5.507,
      "reason": "FIXED STOP",
      "bars": 3,
      "entry_bar": 163,
      "exit_bar": 166,
      "size": 486.867,
      "equity_after": 460.0553
    },
    {
      "pair": "GAIB/USD",
      "entry": 0.0456,
      "exit": 0.0433,
      "pnl": -32.2259,
      "pnl_pct": -5.507,
      "reason": "FIXED STOP",
      "bars": 20,
      "entry_bar": 158,
      "exit_bar": 178,
      "size": 585.1807,
      "equity_after": 552.9548
    },
    {
      "pair": "NEAR/USD",
      "entry": 2.529,
      "exit": 2.4025,
      "pnl": -30.4512,
      "pnl_pct": -5.507,
      "reason": "FIXED STOP",
      "bars": 4,
      "entry_bar": 178,
      "exit_bar": 182,
      "size": 552.9548,
      "equity_after": 522.5035
    },
    {
      "pair": "BMB/USD",
      "entry": 0.0089,
      "exit": 0.0088,
      "pnl": -9.6327,
      "pnl_pct": -1.9785,
      "reason": "TIME MAX",
      "bars": 20,
      "entry_bar": 163,
      "exit_bar": 183,
      "size": 486.867,
      "equity_after": 477.2343
    },
    {
      "pair": "FIS/USD",
      "entry": 0.0624,
      "exit": 0.0674,
      "pnl": 38.9746,
      "pnl_pct": 7.4592,
      "reason": "PROFIT TARGET",
      "bars": 1,
      "entry_bar": 182,
      "exit_bar": 183,
      "size": 522.5035,
      "equity_after": 1038.7124
    },
    {
      "pair": "0G/USD",
      "entry": 1.374,
      "exit": 1.3053,
      "pnl": -28.6009,
      "pnl_pct": -5.507,
      "reason": "FIXED STOP",
      "bars": 2,
      "entry_bar": 183,
      "exit_bar": 185,
      "size": 519.3562,
      "equity_after": 490.7553
    },
    {
      "pair": "HOLO/USD",
      "entry": 0.0819,
      "exit": 0.0789,
      "pnl": -19.2003,
      "pnl_pct": -4.1735,
      "reason": "TIME MAX",
      "bars": 20,
      "entry_bar": 166,
      "exit_bar": 186,
      "size": 460.0553,
      "equity_after": 440.8549
    },
    {
      "pair": "BICO/USD",
      "entry": 0.057,
      "exit": 0.0541,
      "pnl": -28.6009,
      "pnl_pct": -5.507,
      "reason": "FIXED STOP",
      "bars": 4,
      "entry_bar": 183,
      "exit_bar": 187,
      "size": 519.3562,
      "equity_after": 490.7553
    },
    {
      "pair": "TERM/USD",
      "entry": 0.667,
      "exit": 0.6337,
      "pnl": -27.0259,
      "pnl_pct": -5.507,
      "reason": "FIXED STOP",
      "bars": 6,
      "entry_bar": 185,
      "exit_bar": 191,
      "size": 490.7553,
      "equity_after": 463.7294
    },
    {
      "pair": "TREE/USD",
      "entry": 0.1483,
      "exit": 0.1409,
      "pnl": -24.2779,
      "pnl_pct": -5.507,
      "reason": "FIXED STOP",
      "bars": 7,
      "entry_bar": 186,
      "exit_bar": 193,
      "size": 440.8549,
      "equity_after": 416.5771
    },
    {
      "pair": "AVAAI/USD",
      "entry": 0.0126,
      "exit": 0.012,
      "pnl": -25.5376,
      "pnl_pct": -5.507,
      "reason": "FIXED STOP",
      "bars": 2,
      "entry_bar": 191,
      "exit_bar": 193,
      "size": 463.7294,
      "equity_after": 854.7689
    },
    {
      "pair": "REP/USD",
      "entry": 1.633,
      "exit": 1.5514,
      "pnl": -23.5361,
      "pnl_pct": -5.507,
      "reason": "FIXED STOP",
      "bars": 1,
      "entry_bar": 193,
      "exit_bar": 194,
      "size": 427.3844,
      "equity_after": 403.8484
    },
    {
      "pair": "SYN/USD",
      "entry": 0.066,
      "exit": 0.0627,
      "pnl": -22.2399,
      "pnl_pct": -5.507,
      "reason": "FIXED STOP",
      "bars": 8,
      "entry_bar": 194,
      "exit_bar": 202,
      "size": 403.8484,
      "equity_after": 381.6084
    },
    {
      "pair": "IP/USD",
      "entry": 2.8996,
      "exit": 2.7546,
      "pnl": -21.0152,
      "pnl_pct": -5.507,
      "reason": "FIXED STOP",
      "bars": 2,
      "entry_bar": 202,
      "exit_bar": 204,
      "size": 381.6084,
      "equity_after": 360.5933
    },
    {
      "pair": "NTRN/USD",
      "entry": 0.036,
      "exit": 0.0342,
      "pnl": -19.8579,
      "pnl_pct": -5.507,
      "reason": "FIXED STOP",
      "bars": 1,
      "entry_bar": 204,
      "exit_bar": 205,
      "size": 360.5933,
      "equity_after": 340.7354
    },
    {
      "pair": "MIM/USD",
      "entry": 0.0005,
      "exit": 0.0005,
      "pnl": -18.7643,
      "pnl_pct": -5.507,
      "reason": "FIXED STOP",
      "bars": 1,
      "entry_bar": 205,
      "exit_bar": 206,
      "size": 340.7354,
      "equity_after": 321.9711
    },
    {
      "pair": "SBR/USD",
      "entry": 0.0009,
      "exit": 0.0009,
      "pnl": -6.8836,
      "pnl_pct": -1.4027,
      "reason": "TIME MAX",
      "bars": 20,
      "entry_bar": 187,
      "exit_bar": 207,
      "size": 490.7553,
      "equity_after": 483.8717
    },
    {
      "pair": "SDN/USD",
      "entry": 0.0231,
      "exit": 0.0219,
      "pnl": -17.7309,
      "pnl_pct": -5.507,
      "reason": "FIXED STOP",
      "bars": 1,
      "entry_bar": 206,
      "exit_bar": 207,
      "size": 321.9711,
      "equity_after": 788.1118
    },
    {
      "pair": "RHEA/USD",
      "entry": 0.0271,
      "exit": 0.0257,
      "pnl": -21.7007,
      "pnl_pct": -5.507,
      "reason": "FIXED STOP",
      "bars": 3,
      "entry_bar": 207,
      "exit_bar": 210,
      "size": 394.0559,
      "equity_after": 372.3552
    },
    {
      "pair": "XL1/USD",
      "entry": 0.0007,
      "exit": 0.0007,
      "pnl": -23.5361,
      "pnl_pct": -5.507,
      "reason": "FIXED STOP",
      "bars": 18,
      "entry_bar": 193,
      "exit_bar": 211,
      "size": 427.3844,
      "equity_after": 403.8484
    },
    {
      "pair": "RED/USD",
      "entry": 0.2793,
      "exit": 0.2653,
      "pnl": -20.5056,
      "pnl_pct": -5.507,
      "reason": "FIXED STOP",
      "bars": 1,
      "entry_bar": 210,
      "exit_bar": 211,
      "size": 372.3552,
      "equity_after": 755.698
    },
    {
      "pair": "FIDA/USD",
      "entry": 0.0485,
      "exit": 0.0461,
      "pnl": -20.8081,
      "pnl_pct": -5.507,
      "reason": "FIXED STOP",
      "bars": 2,
      "entry_bar": 211,
      "exit_bar": 213,
      "size": 377.849,
      "equity_after": 357.0409
    },
    {
      "pair": "SSV/USD",
      "entry": 3.856,
      "exit": 3.6632,
      "pnl": -21.7007,
      "pnl_pct": -5.507,
      "reason": "FIXED STOP",
      "bars": 7,
      "entry_bar": 207,
      "exit_bar": 214,
      "size": 394.0559,
      "equity_after": 372.3552
    },
    {
      "pair": "CLOUD/USD",
      "entry": 0.0798,
      "exit": 0.0758,
      "pnl": -20.5056,
      "pnl_pct": -5.507,
      "reason": "FIXED STOP",
      "bars": 2,
      "entry_bar": 214,
      "exit_bar": 216,
      "size": 372.3552,
      "equity_after": 351.8496
    },
    {
      "pair": "KOBAN/USD",
      "entry": 0.0007,
      "exit": 0.0006,
      "pnl": -19.3764,
      "pnl_pct": -5.507,
      "reason": "FIXED STOP",
      "bars": 1,
      "entry_bar": 216,
      "exit_bar": 217,
      "size": 351.8496,
      "equity_after": 332.4733
    },
    {
      "pair": "CORN/USD",
      "entry": 0.0769,
      "exit": 0.0731,
      "pnl": -18.3093,
      "pnl_pct": -5.507,
      "reason": "FIXED STOP",
      "bars": 5,
      "entry_bar": 217,
      "exit_bar": 222,
      "size": 332.4733,
      "equity_after": 314.164
    },
    {
      "pair": "DAG/USD",
      "entry": 0.0118,
      "exit": 0.0128,
      "pnl": 26.6324,
      "pnl_pct": 7.4592,
      "reason": "PROFIT TARGET",
      "bars": 10,
      "entry_bar": 213,
      "exit_bar": 223,
      "size": 357.0409,
      "equity_after": 383.6733
    },
    {
      "pair": "STABLE/USD",
      "entry": 0.0148,
      "exit": 0.016,
      "pnl": 28.1845,
      "pnl_pct": 7.4592,
      "reason": "PROFIT TARGET",
      "bars": 13,
      "entry_bar": 211,
      "exit_bar": 224,
      "size": 377.849,
      "equity_after": 406.0335
    },
    {
      "pair": "AIN/USD",
      "entry": 0.0621,
      "exit": 0.067,
      "pnl": 28.619,
      "pnl_pct": 7.4592,
      "reason": "PROFIT TARGET",
      "bars": 1,
      "entry_bar": 223,
      "exit_bar": 224,
      "size": 383.6733,
      "equity_after": 818.3257
    },
    {
      "pair": "DMC/USD",
      "entry": 0.0016,
      "exit": 0.0017,
      "pnl": 30.5203,
      "pnl_pct": 7.4592,
      "reason": "PROFIT TARGET",
      "bars": 1,
      "entry_bar": 225,
      "exit_bar": 226,
      "size": 409.1629,
      "equity_after": 439.6831
    },
    {
      "pair": "EPT/USD",
      "entry": 0.0028,
      "exit": 0.0027,
      "pnl": -24.2134,
      "pnl_pct": -5.507,
      "reason": "FIXED STOP",
      "bars": 3,
      "entry_bar": 226,
      "exit_bar": 229,
      "size": 439.6831,
      "equity_after": 415.4698
    },
    {
      "pair": "RBC/USD",
      "entry": 0.0061,
      "exit": 0.0058,
      "pnl": -22.8799,
      "pnl_pct": -5.507,
      "reason": "FIXED STOP",
      "bars": 3,
      "entry_bar": 229,
      "exit_bar": 232,
      "size": 415.4698,
      "equity_after": 392.5899
    },
    {
      "pair": "ORDER/USD",
      "entry": 0.1225,
      "exit": 0.1323,
      "pnl": 29.2841,
      "pnl_pct": 7.4592,
      "reason": "PROFIT TARGET",
      "bars": 1,
      "entry_bar": 232,
      "exit_bar": 233,
      "size": 392.5899,
      "equity_after": 421.8739
    },
    {
      "pair": "EDGE/USD",
      "entry": 0.1535,
      "exit": 0.1458,
      "pnl": -22.5326,
      "pnl_pct": -5.507,
      "reason": "FIXED STOP",
      "bars": 9,
      "entry_bar": 225,
      "exit_bar": 234,
      "size": 409.1629,
      "equity_after": 386.6303
    },
    {
      "pair": "DOLO/USD",
      "entry": 0.0467,
      "exit": 0.0504,
      "pnl": 31.4684,
      "pnl_pct": 7.4592,
      "reason": "PROFIT TARGET",
      "bars": 1,
      "entry_bar": 233,
      "exit_bar": 234,
      "size": 421.8739,
      "equity_after": 839.9726
    },
    {
      "pair": "BRL1/USD",
      "entry": 0.1859,
      "exit": 0.1864,
      "pnl": -0.7065,
      "pnl_pct": -0.2249,
      "reason": "TIME MAX",
      "bars": 20,
      "entry_bar": 222,
      "exit_bar": 242,
      "size": 314.164,
      "equity_after": 313.4575
    },
    {
      "pair": "UNITE/USD",
      "entry": 0.0002,
      "exit": 0.0002,
      "pnl": -23.1286,
      "pnl_pct": -5.507,
      "reason": "FIXED STOP",
      "bars": 8,
      "entry_bar": 234,
      "exit_bar": 242,
      "size": 419.9863,
      "equity_after": 710.3152
    },
    {
      "pair": "FLUX/USD",
      "entry": 0.1183,
      "exit": 0.1191,
      "pnl": 0.6488,
      "pnl_pct": 0.1545,
      "reason": "TIME MAX",
      "bars": 20,
      "entry_bar": 234,
      "exit_bar": 254,
      "size": 419.9863,
      "equity_after": 420.6351
    },
    {
      "pair": "HMSTR/USD",
      "entry": 0.0003,
      "exit": 0.0002,
      "pnl": -19.5585,
      "pnl_pct": -5.507,
      "reason": "FIXED STOP",
      "bars": 18,
      "entry_bar": 242,
      "exit_bar": 260,
      "size": 355.1576,
      "equity_after": 335.599
    },
    {
      "pair": "T/USD",
      "entry": 0.0115,
      "exit": 0.0113,
      "pnl": -9.8348,
      "pnl_pct": -2.7691,
      "reason": "TIME MAX",
      "bars": 20,
      "entry_bar": 242,
      "exit_bar": 262,
      "size": 355.1576,
      "equity_after": 345.3228
    },
    {
      "pair": "CHECK/USD",
      "entry": 0.0569,
      "exit": 0.054,
      "pnl": -18.4814,
      "pnl_pct": -5.507,
      "reason": "FIXED STOP",
      "bars": 3,
      "entry_bar": 260,
      "exit_bar": 263,
      "size": 335.599,
      "equity_after": 317.1176
    },
    {
      "pair": "PIPE/USD",
      "entry": 0.0642,
      "exit": 0.0694,
      "pnl": 25.7583,
      "pnl_pct": 7.4592,
      "reason": "PROFIT TARGET",
      "bars": 1,
      "entry_bar": 262,
      "exit_bar": 263,
      "size": 345.3228,
      "equity_after": 688.1987
    },
    {
      "pair": "MXC/USD",
      "entry": 0.001,
      "exit": 0.0011,
      "pnl": 25.6671,
      "pnl_pct": 7.4592,
      "reason": "PROFIT TARGET",
      "bars": 1,
      "entry_bar": 263,
      "exit_bar": 264,
      "size": 344.0994,
      "equity_after": 369.7664
    },
    {
      "pair": "ICNT/USD",
      "entry": 0.3112,
      "exit": 0.3361,
      "pnl": 27.5816,
      "pnl_pct": 7.4592,
      "reason": "PROFIT TARGET",
      "bars": 1,
      "entry_bar": 264,
      "exit_bar": 265,
      "size": 369.7664,
      "equity_after": 397.3481
    },
    {
      "pair": "HOLO/USD",
      "entry": 0.069,
      "exit": 0.0655,
      "pnl": -23.1644,
      "pnl_pct": -5.507,
      "reason": "FIXED STOP",
      "bars": 15,
      "entry_bar": 254,
      "exit_bar": 269,
      "size": 420.6351,
      "equity_after": 397.4708
    },
    {
      "pair": "SUKU/USD",
      "entry": 0.0142,
      "exit": 0.0153,
      "pnl": 25.6671,
      "pnl_pct": 7.4592,
      "reason": "PROFIT TARGET",
      "bars": 7,
      "entry_bar": 263,
      "exit_bar": 270,
      "size": 344.0994,
      "equity_after": 369.7664
    },
    {
      "pair": "LION/USD",
      "entry": 0.0074,
      "exit": 0.007,
      "pnl": -21.8887,
      "pnl_pct": -5.507,
      "reason": "FIXED STOP",
      "bars": 1,
      "entry_bar": 269,
      "exit_bar": 270,
      "size": 397.4708,
      "equity_after": 745.3485
    },
    {
      "pair": "NOS/USD",
      "entry": 0.288,
      "exit": 0.2736,
      "pnl": -20.5232,
      "pnl_pct": -5.507,
      "reason": "FIXED STOP",
      "bars": 3,
      "entry_bar": 270,
      "exit_bar": 273,
      "size": 372.6742,
      "equity_after": 352.1511
    },
    {
      "pair": "ZRO/USD",
      "entry": 1.35,
      "exit": 1.2825,
      "pnl": -19.393,
      "pnl_pct": -5.507,
      "reason": "FIXED STOP",
      "bars": 1,
      "entry_bar": 273,
      "exit_bar": 274,
      "size": 352.1511,
      "equity_after": 332.7581
    },
    {
      "pair": "EAT/USD",
      "entry": 0.0357,
      "exit": 0.0339,
      "pnl": -20.5232,
      "pnl_pct": -5.507,
      "reason": "FIXED STOP",
      "bars": 6,
      "entry_bar": 270,
      "exit_bar": 276,
      "size": 372.6742,
      "equity_after": 352.1511
    },
    {
      "pair": "DYM/USD",
      "entry": 0.0962,
      "exit": 0.0914,
      "pnl": -18.325,
      "pnl_pct": -5.507,
      "reason": "FIXED STOP",
      "bars": 2,
      "entry_bar": 274,
      "exit_bar": 276,
      "size": 332.7581,
      "equity_after": 666.5842
    },
    {
      "pair": "UNITE/USD",
      "entry": 0.0002,
      "exit": 0.0002,
      "pnl": -18.3544,
      "pnl_pct": -5.507,
      "reason": "FIXED STOP",
      "bars": 1,
      "entry_bar": 276,
      "exit_bar": 277,
      "size": 333.2921,
      "equity_after": 314.9377
    },
    {
      "pair": "YALA/USD",
      "entry": 0.0293,
      "exit": 0.0278,
      "pnl": -17.3436,
      "pnl_pct": -5.507,
      "reason": "FIXED STOP",
      "bars": 5,
      "entry_bar": 277,
      "exit_bar": 282,
      "size": 314.9377,
      "equity_after": 297.5941
    },
    {
      "pair": "TERM/USD",
      "entry": 0.663,
      "exit": 0.663,
      "pnl": -2.0662,
      "pnl_pct": -0.52,
      "reason": "TIME MAX",
      "bars": 20,
      "entry_bar": 265,
      "exit_bar": 285,
      "size": 397.3481,
      "equity_after": 395.2818
    },
    {
      "pair": "ZBT/USD",
      "entry": 0.117,
      "exit": 0.1111,
      "pnl": -21.7682,
      "pnl_pct": -5.507,
      "reason": "FIXED STOP",
      "bars": 4,
      "entry_bar": 285,
      "exit_bar": 289,
      "size": 395.2818,
      "equity_after": 373.5137
    },
    {
      "pair": "TERM/USD",
      "entry": 0.662,
      "exit": 0.6289,
      "pnl": -20.5694,
      "pnl_pct": -5.507,
      "reason": "FIXED STOP",
      "bars": 1,
      "entry_bar": 289,
      "exit_bar": 290,
      "size": 373.5137,
      "equity_after": 352.9443
    },
    {
      "pair": "AIN/USD",
      "entry": 0.0504,
      "exit": 0.0479,
      "pnl": -19.4366,
      "pnl_pct": -5.507,
      "reason": "FIXED STOP",
      "bars": 2,
      "entry_bar": 290,
      "exit_bar": 292,
      "size": 352.9443,
      "equity_after": 333.5076
    },
    {
      "pair": "XAUT/USD",
      "entry": 4220.3,
      "exit": 4202.5,
      "pnl": -3.1352,
      "pnl_pct": -0.9407,
      "reason": "TIME MAX",
      "bars": 20,
      "entry_bar": 276,
      "exit_bar": 296,
      "size": 333.2921,
      "equity_after": 330.1569
    },
    {
      "pair": "EPT/USD",
      "entry": 0.0023,
      "exit": 0.0022,
      "pnl": -18.1817,
      "pnl_pct": -5.507,
      "reason": "FIXED STOP",
      "bars": 5,
      "entry_bar": 296,
      "exit_bar": 301,
      "size": 330.1569,
      "equity_after": 311.9752
    },
    {
      "pair": "VSN/USD",
      "entry": 0.0928,
      "exit": 0.0912,
      "pnl": -6.8547,
      "pnl_pct": -2.3034,
      "reason": "TIME MAX",
      "bars": 20,
      "entry_bar": 282,
      "exit_bar": 302,
      "size": 297.5941,
      "equity_after": 290.7394
    },
    {
      "pair": "BIT/USD",
      "entry": 1.0668,
      "exit": 1.1521,
      "pnl": 23.2709,
      "pnl_pct": 7.4592,
      "reason": "PROFIT TARGET",
      "bars": 1,
      "entry_bar": 301,
      "exit_bar": 302,
      "size": 311.9752,
      "equity_after": 625.9854
    },
    {
      "pair": "UXLINK/USD",
      "entry": 0.0143,
      "exit": 0.0154,
      "pnl": 23.3468,
      "pnl_pct": 7.4592,
      "reason": "PROFIT TARGET",
      "bars": 1,
      "entry_bar": 302,
      "exit_bar": 303,
      "size": 312.9927,
      "equity_after": 336.3394
    },
    {
      "pair": "WEN/USD",
      "entry": 0.0,
      "exit": 0.0,
      "pnl": -18.5222,
      "pnl_pct": -5.507,
      "reason": "FIXED STOP",
      "bars": 1,
      "entry_bar": 303,
      "exit_bar": 304,
      "size": 336.3394,
      "equity_after": 317.8172
    },
    {
      "pair": "MOON/USD",
      "entry": 0.0534,
      "exit": 0.0507,
      "pnl": -17.5022,
      "pnl_pct": -5.507,
      "reason": "FIXED STOP",
      "bars": 2,
      "entry_bar": 304,
      "exit_bar": 306,
      "size": 317.8172,
      "equity_after": 300.315
    },
    {
      "pair": "SOGNI/USD",
      "entry": 0.0033,
      "exit": 0.0033,
      "pnl": -4.0283,
      "pnl_pct": -1.2079,
      "reason": "TIME MAX",
      "bars": 20,
      "entry_bar": 292,
      "exit_bar": 312,
      "size": 333.5076,
      "equity_after": 329.4793
    },
    {
      "pair": "AIOZ/USD",
      "entry": 0.1169,
      "exit": 0.1263,
      "pnl": 24.5765,
      "pnl_pct": 7.4592,
      "reason": "PROFIT TARGET",
      "bars": 6,
      "entry_bar": 312,
      "exit_bar": 318,
      "size": 329.4793,
      "equity_after": 354.0558
    },
    {
      "pair": "STEP/USD",
      "entry": 0.0191,
      "exit": 0.0181,
      "pnl": -17.2365,
      "pnl_pct": -5.507,
      "reason": "FIXED STOP",
      "bars": 18,
      "entry_bar": 302,
      "exit_bar": 320,
      "size": 312.9927,
      "equity_after": 295.7562
    },
    {
      "pair": "CHZ/USD",
      "entry": 0.0308,
      "exit": 0.0333,
      "pnl": 22.4011,
      "pnl_pct": 7.4592,
      "reason": "PROFIT TARGET",
      "bars": 15,
      "entry_bar": 306,
      "exit_bar": 321,
      "size": 300.315,
      "equity_after": 322.7161
    },
    {
      "pair": "SONIC/USD",
      "entry": 0.0824,
      "exit": 0.0889,
      "pnl": 24.072,
      "pnl_pct": 7.4592,
      "reason": "PROFIT TARGET",
      "bars": 4,
      "entry_bar": 321,
      "exit_bar": 325,
      "size": 322.7161,
      "equity_after": 346.7882
    },
    {
      "pair": "DUCK/USD",
      "entry": 0.0013,
      "exit": 0.0013,
      "pnl": -19.0976,
      "pnl_pct": -5.507,
      "reason": "FIXED STOP",
      "bars": 1,
      "entry_bar": 325,
      "exit_bar": 326,
      "size": 346.7882,
      "equity_after": 327.6906
    },
    {
      "pair": "SIGMA/USD",
      "entry": 0.0041,
      "exit": 0.0039,
      "pnl": -16.2873,
      "pnl_pct": -5.507,
      "reason": "FIXED STOP",
      "bars": 13,
      "entry_bar": 320,
      "exit_bar": 333,
      "size": 295.7562,
      "equity_after": 279.4689
    },
    {
      "pair": "KAVA/USD",
      "entry": 0.1107,
      "exit": 0.1052,
      "pnl": -18.0459,
      "pnl_pct": -5.507,
      "reason": "FIXED STOP",
      "bars": 7,
      "entry_bar": 326,
      "exit_bar": 333,
      "size": 327.6906,
      "equity_after": 589.1135
    },
    {
      "pair": "DOLO/USD",
      "entry": 0.041,
      "exit": 0.0389,
      "pnl": -19.4979,
      "pnl_pct": -5.507,
      "reason": "FIXED STOP",
      "bars": 16,
      "entry_bar": 318,
      "exit_bar": 334,
      "size": 354.0558,
      "equity_after": 334.558
    },
    {
      "pair": "OBOL/USD",
      "entry": 0.0259,
      "exit": 0.0279,
      "pnl": 21.9716,
      "pnl_pct": 7.4592,
      "reason": "PROFIT TARGET",
      "bars": 3,
      "entry_bar": 333,
      "exit_bar": 336,
      "size": 294.5568,
      "equity_after": 316.5283
    },
    {
      "pair": "STABLE/USD",
      "entry": 0.0266,
      "exit": 0.0287,
      "pnl": 24.9553,
      "pnl_pct": 7.4592,
      "reason": "PROFIT TARGET",
      "bars": 2,
      "entry_bar": 334,
      "exit_bar": 336,
      "size": 334.558,
      "equity_after": 676.0417
    },
    {
      "pair": "VANRY/USD",
      "entry": 0.0109,
      "exit": 0.0104,
      "pnl": -18.6148,
      "pnl_pct": -5.507,
      "reason": "FIXED STOP",
      "bars": 1,
      "entry_bar": 336,
      "exit_bar": 337,
      "size": 338.0208,
      "equity_after": 319.406
    },
    {
      "pair": "FIS/USD",
      "entry": 0.0306,
      "exit": 0.0291,
      "pnl": -18.6148,
      "pnl_pct": -5.507,
      "reason": "FIXED STOP",
      "bars": 1,
      "entry_bar": 336,
      "exit_bar": 337,
      "size": 338.0208,
      "equity_after": 638.8121
    },
    {
      "pair": "SIDEKICK/USD",
      "entry": 0.0067,
      "exit": 0.0063,
      "pnl": -17.5897,
      "pnl_pct": -5.507,
      "reason": "FIXED STOP",
      "bars": 6,
      "entry_bar": 337,
      "exit_bar": 343,
      "size": 319.406,
      "equity_after": 301.8163
    },
    {
      "pair": "BTT/USD",
      "entry": 0.0,
      "exit": 0.0,
      "pnl": -14.8222,
      "pnl_pct": -5.032,
      "reason": "TIME MAX",
      "bars": 20,
      "entry_bar": 333,
      "exit_bar": 353,
      "size": 294.5568,
      "equity_after": 279.7345
    },
    {
      "pair": "GLMR/USD",
      "entry": 0.0313,
      "exit": 0.0297,
      "pnl": -15.405,
      "pnl_pct": -5.507,
      "reason": "FIXED STOP",
      "bars": 1,
      "entry_bar": 353,
      "exit_bar": 354,
      "size": 279.7345,
      "equity_after": 264.3295
    },
    {
      "pair": "MYX/USD",
      "entry": 3.088,
      "exit": 3.335,
      "pnl": 19.7169,
      "pnl_pct": 7.4592,
      "reason": "PROFIT TARGET",
      "bars": 1,
      "entry_bar": 354,
      "exit_bar": 355,
      "size": 264.3295,
      "equity_after": 284.0464
    },
    {
      "pair": "STEP/USD",
      "entry": 0.0175,
      "exit": 0.0174,
      "pnl": -3.4813,
      "pnl_pct": -1.0899,
      "reason": "TIME MAX",
      "bars": 20,
      "entry_bar": 337,
      "exit_bar": 357,
      "size": 319.406,
      "equity_after": 315.9247
    },
    {
      "pair": "SIGMA/USD",
      "entry": 0.0039,
      "exit": 0.0037,
      "pnl": -15.6424,
      "pnl_pct": -5.507,
      "reason": "FIXED STOP",
      "bars": 5,
      "entry_bar": 355,
      "exit_bar": 360,
      "size": 284.0464,
      "equity_after": 268.404
    },
    {
      "pair": "AB/USD",
      "entry": 0.0053,
      "exit": 0.0053,
      "pnl": -4.4986,
      "pnl_pct": -1.4905,
      "reason": "TIME MAX",
      "bars": 20,
      "entry_bar": 343,
      "exit_bar": 363,
      "size": 301.8163,
      "equity_after": 297.3177
    },
    {
      "pair": "ANIME/USD",
      "entry": 0.0055,
      "exit": 0.0059,
      "pnl": 20.0208,
      "pnl_pct": 7.4592,
      "reason": "PROFIT TARGET",
      "bars": 3,
      "entry_bar": 360,
      "exit_bar": 363,
      "size": 268.404,
      "equity_after": 585.7425
    },
    {
      "pair": "ENSO/USD",
      "entry": 0.704,
      "exit": 0.7603,
      "pnl": 21.8459,
      "pnl_pct": 7.4592,
      "reason": "PROFIT TARGET",
      "bars": 1,
      "entry_bar": 363,
      "exit_bar": 364,
      "size": 292.8712,
      "equity_after": 314.7171
    },
    {
      "pair": "KEY/USD",
      "entry": 0.0003,
      "exit": 0.0002,
      "pnl": -17.3315,
      "pnl_pct": -5.507,
      "reason": "FIXED STOP",
      "bars": 1,
      "entry_bar": 364,
      "exit_bar": 365,
      "size": 314.7171,
      "equity_after": 297.3856
    },
    {
      "pair": "ACT/USD",
      "entry": 0.0214,
      "exit": 0.0203,
      "pnl": -16.377,
      "pnl_pct": -5.507,
      "reason": "FIXED STOP",
      "bars": 2,
      "entry_bar": 365,
      "exit_bar": 367,
      "size": 297.3856,
      "equity_after": 281.0086
    },
    {
      "pair": "UAI/USD",
      "entry": 0.1681,
      "exit": 0.1597,
      "pnl": -16.1284,
      "pnl_pct": -5.507,
      "reason": "FIXED STOP",
      "bars": 6,
      "entry_bar": 363,
      "exit_bar": 369,
      "size": 292.8712,
      "equity_after": 276.7428
    },
    {
      "pair": "AIR/USD",
      "entry": 0.0014,
      "exit": 0.0016,
      "pnl": 20.6428,
      "pnl_pct": 7.4592,
      "reason": "PROFIT TARGET",
      "bars": 4,
      "entry_bar": 369,
      "exit_bar": 373,
      "size": 276.7428,
      "equity_after": 297.3856
    },
    {
      "pair": "OMG/USD",
      "entry": 0.0859,
      "exit": 0.0816,
      "pnl": -16.377,
      "pnl_pct": -5.507,
      "reason": "FIXED STOP",
      "bars": 1,
      "entry_bar": 373,
      "exit_bar": 374,
      "size": 297.3856,
      "equity_after": 281.0086
    },
    {
      "pair": "FOREST/USD",
      "entry": 0.033,
      "exit": 0.0331,
      "pnl": -0.4,
      "pnl_pct": -0.1266,
      "reason": "TIME MAX",
      "bars": 20,
      "entry_bar": 357,
      "exit_bar": 377,
      "size": 315.9247,
      "equity_after": 315.5247
    },
    {
      "pair": "YALA/USD",
      "entry": 0.0205,
      "exit": 0.0195,
      "pnl": -15.4751,
      "pnl_pct": -5.507,
      "reason": "FIXED STOP",
      "bars": 3,
      "entry_bar": 374,
      "exit_bar": 377,
      "size": 281.0086,
      "equity_after": 581.0582
    },
    {
      "pair": "SBR/USD",
      "entry": 0.0009,
      "exit": 0.0009,
      "pnl": -15.4751,
      "pnl_pct": -5.507,
      "reason": "FIXED STOP",
      "bars": 11,
      "entry_bar": 367,
      "exit_bar": 378,
      "size": 281.0086,
      "equity_after": 265.5334
    },
    {
      "pair": "LRC/USD",
      "entry": 0.0584,
      "exit": 0.0631,
      "pnl": 21.6711,
      "pnl_pct": 7.4592,
      "reason": "PROFIT TARGET",
      "bars": 2,
      "entry_bar": 377,
      "exit_bar": 379,
      "size": 290.5291,
      "equity_after": 312.2002
    },
    {
      "pair": "BCH/USD",
      "entry": 561.65,
      "exit": 606.582,
      "pnl": 23.2876,
      "pnl_pct": 7.4592,
      "reason": "PROFIT TARGET",
      "bars": 6,
      "entry_bar": 379,
      "exit_bar": 385,
      "size": 312.2002,
      "equity_after": 335.4879
    },
    {
      "pair": "PROMPT/USD",
      "entry": 0.0539,
      "exit": 0.0513,
      "pnl": -18.4753,
      "pnl_pct": -5.507,
      "reason": "FIXED STOP",
      "bars": 1,
      "entry_bar": 385,
      "exit_bar": 386,
      "size": 335.4879,
      "equity_after": 317.0125
    },
    {
      "pair": "TOKEN/USD",
      "entry": 0.0025,
      "exit": 0.0027,
      "pnl": 23.6466,
      "pnl_pct": 7.4592,
      "reason": "PROFIT TARGET",
      "bars": 4,
      "entry_bar": 386,
      "exit_bar": 390,
      "size": 317.0125,
      "equity_after": 340.6591
    },
    {
      "pair": "RHEA/USD",
      "entry": 0.0154,
      "exit": 0.0158,
      "pnl": 6.209,
      "pnl_pct": 2.1371,
      "reason": "TIME MAX",
      "bars": 20,
      "entry_bar": 377,
      "exit_bar": 397,
      "size": 290.5291,
      "equity_after": 296.7381
    },
    {
      "pair": "SCA/USD",
      "entry": 0.0415,
      "exit": 0.0406,
      "pnl": -7.1244,
      "pnl_pct": -2.683,
      "reason": "TIME MAX",
      "bars": 20,
      "entry_bar": 378,
      "exit_bar": 398,
      "size": 265.5334,
      "equity_after": 258.4091
    },
    {
      "pair": "EDU/USD",
      "entry": 0.1605,
      "exit": 0.1525,
      "pnl": -16.3414,
      "pnl_pct": -5.507,
      "reason": "FIXED STOP",
      "bars": 2,
      "entry_bar": 397,
      "exit_bar": 399,
      "size": 296.7381,
      "equity_after": 280.3967
    },
    {
      "pair": "AIN/USD",
      "entry": 0.0553,
      "exit": 0.0525,
      "pnl": -14.2306,
      "pnl_pct": -5.507,
      "reason": "FIXED STOP",
      "bars": 11,
      "entry_bar": 398,
      "exit_bar": 409,
      "size": 258.4091,
      "equity_after": 244.1785
    },
    {
      "pair": "LIT/USD",
      "entry": 0.1176,
      "exit": 0.127,
      "pnl": 20.9154,
      "pnl_pct": 7.4592,
      "reason": "PROFIT TARGET",
      "bars": 10,
      "entry_bar": 399,
      "exit_bar": 409,
      "size": 280.3967,
      "equity_after": 545.4906
    },
    {
      "pair": "ARPA/USD",
      "entry": 0.0124,
      "exit": 0.0124,
      "pnl": -3.1393,
      "pnl_pct": -0.9215,
      "reason": "TIME MAX",
      "bars": 20,
      "entry_bar": 390,
      "exit_bar": 410,
      "size": 340.6591,
      "equity_after": 337.5199
    },
    {
      "pair": "VELODROME/USD",
      "entry": 0.0202,
      "exit": 0.0192,
      "pnl": -18.5872,
      "pnl_pct": -5.507,
      "reason": "FIXED STOP",
      "bars": 3,
      "entry_bar": 410,
      "exit_bar": 413,
      "size": 337.5199,
      "equity_after": 318.9326
    },
    {
      "pair": "RAD/USD",
      "entry": 0.265,
      "exit": 0.266,
      "pnl": -0.3917,
      "pnl_pct": -0.1436,
      "reason": "TIME MAX",
      "bars": 20,
      "entry_bar": 409,
      "exit_bar": 429,
      "size": 272.7453,
      "equity_after": 272.3536
    },
    {
      "pair": "SUKU/USD",
      "entry": 0.01,
      "exit": 0.0099,
      "pnl": -3.0554,
      "pnl_pct": -1.1202,
      "reason": "TIME MAX",
      "bars": 20,
      "entry_bar": 409,
      "exit_bar": 429,
      "size": 272.7453,
      "equity_after": 542.0434
    },
    {
      "pair": "VULT/USD",
      "entry": 0.1034,
      "exit": 0.1038,
      "pnl": -0.4279,
      "pnl_pct": -0.1342,
      "reason": "TIME MAX",
      "bars": 20,
      "entry_bar": 413,
      "exit_bar": 433,
      "size": 318.9326,
      "equity_after": 318.5048
    },
    {
      "pair": "BIT/USD",
      "entry": 1.0449,
      "exit": 0.9927,
      "pnl": -17.5401,
      "pnl_pct": -5.507,
      "reason": "FIXED STOP",
      "bars": 1,
      "entry_bar": 433,
      "exit_bar": 434,
      "size": 318.5048,
      "equity_after": 300.9647
    },
    {
      "pair": "HNT/USD",
      "entry": 1.5068,
      "exit": 1.4315,
      "pnl": -16.5741,
      "pnl_pct": -5.507,
      "reason": "FIXED STOP",
      "bars": 1,
      "entry_bar": 434,
      "exit_bar": 435,
      "size": 300.9647,
      "equity_after": 284.3906
    },
    {
      "pair": "ZIG/USD",
      "entry": 0.0585,
      "exit": 0.0632,
      "pnl": 20.2161,
      "pnl_pct": 7.4592,
      "reason": "PROFIT TARGET",
      "bars": 7,
      "entry_bar": 429,
      "exit_bar": 436,
      "size": 271.0217,
      "equity_after": 291.2378
    },
    {
      "pair": "CLV/USD",
      "entry": 0.0048,
      "exit": 0.0052,
      "pnl": 21.724,
      "pnl_pct": 7.4592,
      "reason": "PROFIT TARGET",
      "bars": 1,
      "entry_bar": 436,
      "exit_bar": 437,
      "size": 291.2378,
      "equity_after": 312.9618
    },
    {
      "pair": "PRO/USD",
      "entry": 0.3407,
      "exit": 0.3237,
      "pnl": -15.6614,
      "pnl_pct": -5.507,
      "reason": "FIXED STOP",
      "bars": 10,
      "entry_bar": 435,
      "exit_bar": 445,
      "size": 284.3906,
      "equity_after": 268.7292
    },
    {
      "pair": "ORDER/USD",
      "entry": 0.0983,
      "exit": 0.0934,
      "pnl": -17.2348,
      "pnl_pct": -5.507,
      "reason": "FIXED STOP",
      "bars": 10,
      "entry_bar": 437,
      "exit_bar": 447,
      "size": 312.9618,
      "equity_after": 295.727
    },
    {
      "pair": "ME/USD",
      "entry": 0.2069,
      "exit": 0.2001,
      "pnl": -10.2936,
      "pnl_pct": -3.7981,
      "reason": "TIME MAX",
      "bars": 20,
      "entry_bar": 429,
      "exit_bar": 449,
      "size": 271.0217,
      "equity_after": 260.7281
    },
    {
      "pair": "XTER/USD",
      "entry": 0.0302,
      "exit": 0.0326,
      "pnl": 22.0589,
      "pnl_pct": 7.4592,
      "reason": "PROFIT TARGET",
      "bars": 2,
      "entry_bar": 447,
      "exit_bar": 449,
      "size": 295.727,
      "equity_after": 578.514
    },
    {
      "pair": "VSN/USD",
      "entry": 0.0827,
      "exit": 0.0893,
      "pnl": 20.045,
      "pnl_pct": 7.4592,
      "reason": "PROFIT TARGET",
      "bars": 13,
      "entry_bar": 445,
      "exit_bar": 458,
      "size": 268.7292,
      "equity_after": 288.7742
    },
    {
      "pair": "XTZ/USD",
      "entry": 0.4972,
      "exit": 0.5146,
      "pnl": 8.5924,
      "pnl_pct": 2.9705,
      "reason": "TIME MAX",
      "bars": 20,
      "entry_bar": 449,
      "exit_bar": 469,
      "size": 289.257,
      "equity_after": 297.8494
    },
    {
      "pair": "A/USD",
      "entry": 0.163,
      "exit": 0.1703,
      "pnl": 11.4166,
      "pnl_pct": 3.9469,
      "reason": "TIME MAX",
      "bars": 20,
      "entry_bar": 449,
      "exit_bar": 469,
      "size": 289.257,
      "equity_after": 598.523
    },
    {
      "pair": "WEN/USD",
      "entry": 0.0,
      "exit": 0.0,
      "pnl": -16.4803,
      "pnl_pct": -5.507,
      "reason": "FIXED STOP",
      "bars": 1,
      "entry_bar": 469,
      "exit_bar": 470,
      "size": 299.2615,
      "equity_after": 282.7812
    },
    {
      "pair": "RARE/USD",
      "entry": 0.0213,
      "exit": 0.0224,
      "pnl": 13.3728,
      "pnl_pct": 4.6309,
      "reason": "TIME MAX",
      "bars": 20,
      "entry_bar": 458,
      "exit_bar": 478,
      "size": 288.7742,
      "equity_after": 302.1471
    },
    {
      "pair": "TNSR/USD",
      "entry": 0.0806,
      "exit": 0.0809,
      "pnl": -0.4452,
      "pnl_pct": -0.1488,
      "reason": "TIME MAX",
      "bars": 20,
      "entry_bar": 469,
      "exit_bar": 489,
      "size": 299.2615,
      "equity_after": 298.8163
    },
    {
      "pair": "GMT/USD",
      "entry": 0.0159,
      "exit": 0.0166,
      "pnl": 11.5033,
      "pnl_pct": 4.0679,
      "reason": "TIME MAX",
      "bars": 20,
      "entry_bar": 470,
      "exit_bar": 490,
      "size": 282.7812,
      "equity_after": 294.2845
    },
    {
      "pair": "DOLO/USD",
      "entry": 0.0473,
      "exit": 0.0451,
      "pnl": -15.9581,
      "pnl_pct": -5.2816,
      "reason": "TIME MAX",
      "bars": 20,
      "entry_bar": 478,
      "exit_bar": 498,
      "size": 302.1471,
      "equity_after": 286.189
    },
    {
      "pair": "QI/USD",
      "entry": 0.0036,
      "exit": 0.0034,
      "pnl": -16.4558,
      "pnl_pct": -5.507,
      "reason": "FIXED STOP",
      "bars": 14,
      "entry_bar": 489,
      "exit_bar": 503,
      "size": 298.8163,
      "equity_after": 282.3605
    },
    {
      "pair": "AUDIO/USD",
      "entry": 0.0316,
      "exit": 0.0341,
      "pnl": 21.3474,
      "pnl_pct": 7.4592,
      "reason": "PROFIT TARGET",
      "bars": 5,
      "entry_bar": 498,
      "exit_bar": 503,
      "size": 286.189,
      "equity_after": 589.8969
    },
    {
      "pair": "SYN/USD",
      "entry": 0.0592,
      "exit": 0.0639,
      "pnl": 21.9513,
      "pnl_pct": 7.4592,
      "reason": "PROFIT TARGET",
      "bars": 16,
      "entry_bar": 490,
      "exit_bar": 506,
      "size": 294.2845,
      "equity_after": 316.2357
    },
    {
      "pair": "CQT/USD",
      "entry": 0.001,
      "exit": 0.001,
      "pnl": -17.4151,
      "pnl_pct": -5.507,
      "reason": "FIXED STOP",
      "bars": 1,
      "entry_bar": 506,
      "exit_bar": 507,
      "size": 316.2357,
      "equity_after": 298.8206
    },
    {
      "pair": "NYM/USD",
      "entry": 0.0375,
      "exit": 0.0356,
      "pnl": -16.2428,
      "pnl_pct": -5.507,
      "reason": "FIXED STOP",
      "bars": 8,
      "entry_bar": 503,
      "exit_bar": 511,
      "size": 294.9484,
      "equity_after": 278.7056
    },
    {
      "pair": "SGB/USD",
      "entry": 0.0026,
      "exit": 0.0025,
      "pnl": -15.3483,
      "pnl_pct": -5.507,
      "reason": "FIXED STOP",
      "bars": 2,
      "entry_bar": 511,
      "exit_bar": 513,
      "size": 278.7056,
      "equity_after": 263.3573
    },
    {
      "pair": "GST/USD",
      "entry": 0.0021,
      "exit": 0.0023,
      "pnl": 19.6443,
      "pnl_pct": 7.4592,
      "reason": "PROFIT TARGET",
      "bars": 2,
      "entry_bar": 513,
      "exit_bar": 515,
      "size": 263.3573,
      "equity_after": 283.0017
    },
    {
      "pair": "SUN/USD",
      "entry": 0.0202,
      "exit": 0.0205,
      "pnl": 4.1601,
      "pnl_pct": 1.4105,
      "reason": "TIME MAX",
      "bars": 20,
      "entry_bar": 503,
      "exit_bar": 523,
      "size": 294.9484,
      "equity_after": 299.1086
    },
    {
      "pair": "REZ/USD",
      "entry": 0.0054,
      "exit": 0.0059,
      "pnl": 21.1097,
      "pnl_pct": 7.4592,
      "reason": "PROFIT TARGET",
      "bars": 8,
      "entry_bar": 515,
      "exit_bar": 523,
      "size": 283.0017,
      "equity_after": 603.2199
    },
    {
      "pair": "ZIG/USD",
      "entry": 0.0603,
      "exit": 0.0592,
      "pnl": -6.9432,
      "pnl_pct": -2.3235,
      "reason": "TIME MAX",
      "bars": 20,
      "entry_bar": 507,
      "exit_bar": 527,
      "size": 298.8206,
      "equity_after": 291.8775
    },
    {
      "pair": "SAPIEN/USD",
      "entry": 0.1433,
      "exit": 0.1362,
      "pnl": -16.6097,
      "pnl_pct": -5.507,
      "reason": "FIXED STOP",
      "bars": 4,
      "entry_bar": 523,
      "exit_bar": 527,
      "size": 301.6099,
      "equity_after": 576.8777
    },
    {
      "pair": "U/USD",
      "entry": 0.0031,
      "exit": 0.0033,
      "pnl": 21.5152,
      "pnl_pct": 7.4592,
      "reason": "PROFIT TARGET",
      "bars": 1,
      "entry_bar": 527,
      "exit_bar": 528,
      "size": 288.4389,
      "equity_after": 309.9541
    },
    {
      "pair": "MOON/USD",
      "entry": 0.0523,
      "exit": 0.0497,
      "pnl": -16.6097,
      "pnl_pct": -5.507,
      "reason": "FIXED STOP",
      "bars": 9,
      "entry_bar": 523,
      "exit_bar": 532,
      "size": 301.6099,
      "equity_after": 285.0003
    },
    {
      "pair": "REKT/USD",
      "entry": 0.0,
      "exit": 0.0,
      "pnl": 21.5152,
      "pnl_pct": 7.4592,
      "reason": "PROFIT TARGET",
      "bars": 7,
      "entry_bar": 527,
      "exit_bar": 534,
      "size": 288.4389,
      "equity_after": 309.9541
    },
    {
      "pair": "FOREST/USD",
      "entry": 0.0246,
      "exit": 0.0266,
      "pnl": 23.1201,
      "pnl_pct": 7.4592,
      "reason": "PROFIT TARGET",
      "bars": 2,
      "entry_bar": 534,
      "exit_bar": 536,
      "size": 309.9541,
      "equity_after": 333.0742
    },
    {
      "pair": "POLIS/USD",
      "entry": 0.0287,
      "exit": 0.0273,
      "pnl": -18.3424,
      "pnl_pct": -5.507,
      "reason": "FIXED STOP",
      "bars": 2,
      "entry_bar": 536,
      "exit_bar": 538,
      "size": 333.0742,
      "equity_after": 314.7318
    },
    {
      "pair": "DUCK/USD",
      "entry": 0.001,
      "exit": 0.0011,
      "pnl": 21.2587,
      "pnl_pct": 7.4592,
      "reason": "PROFIT TARGET",
      "bars": 9,
      "entry_bar": 532,
      "exit_bar": 541,
      "size": 285.0003,
      "equity_after": 306.259
    },
    {
      "pair": "MIRROR/USD",
      "entry": 0.0015,
      "exit": 0.0014,
      "pnl": -16.8657,
      "pnl_pct": -5.507,
      "reason": "FIXED STOP",
      "bars": 1,
      "entry_bar": 541,
      "exit_bar": 542,
      "size": 306.259,
      "equity_after": 289.3933
    },
    {
      "pair": "NOBODY/USD",
      "entry": 0.0133,
      "exit": 0.0126,
      "pnl": -15.9369,
      "pnl_pct": -5.507,
      "reason": "FIXED STOP",
      "bars": 1,
      "entry_bar": 542,
      "exit_bar": 543,
      "size": 289.3933,
      "equity_after": 273.4564
    },
    {
      "pair": "ADX/USD",
      "entry": 0.1033,
      "exit": 0.0982,
      "pnl": -15.0592,
      "pnl_pct": -5.507,
      "reason": "FIXED STOP",
      "bars": 1,
      "entry_bar": 543,
      "exit_bar": 544,
      "size": 273.4564,
      "equity_after": 258.3972
    },
    {
      "pair": "HMSTR/USD",
      "entry": 0.0003,
      "exit": 0.0002,
      "pnl": -17.3323,
      "pnl_pct": -5.507,
      "reason": "FIXED STOP",
      "bars": 7,
      "entry_bar": 538,
      "exit_bar": 545,
      "size": 314.7318,
      "equity_after": 297.3995
    },
    {
      "pair": "NODE/USD",
      "entry": 0.0163,
      "exit": 0.0154,
      "pnl": -14.2299,
      "pnl_pct": -5.507,
      "reason": "FIXED STOP",
      "bars": 1,
      "entry_bar": 544,
      "exit_bar": 545,
      "size": 258.3972,
      "equity_after": 541.5668
    },
    {
      "pair": "AVAX/USD",
      "entry": 13.87,
      "exit": 13.83,
      "pnl": -2.5033,
      "pnl_pct": -0.8076,
      "reason": "TIME MAX",
      "bars": 20,
      "entry_bar": 528,
      "exit_bar": 548,
      "size": 309.9541,
      "equity_after": 307.4508
    },
    {
      "pair": "ACH/USD",
      "entry": 0.0109,
      "exit": 0.0117,
      "pnl": 20.1983,
      "pnl_pct": 7.4592,
      "reason": "PROFIT TARGET",
      "bars": 11,
      "entry_bar": 545,
      "exit_bar": 556,
      "size": 270.7834,
      "equity_after": 290.9817
    },
    {
      "pair": "XTER/USD",
      "entry": 0.0311,
      "exit": 0.0336,
      "pnl": 22.9334,
      "pnl_pct": 7.4592,
      "reason": "PROFIT TARGET",
      "bars": 7,
      "entry_bar": 549,
      "exit_bar": 556,
      "size": 307.4508,
      "equity_after": 621.3658
    },
    {
      "pair": "CHR/USD",
      "entry": 0.0469,
      "exit": 0.0507,
      "pnl": 23.1745,
      "pnl_pct": 7.4592,
      "reason": "PROFIT TARGET",
      "bars": 2,
      "entry_bar": 556,
      "exit_bar": 558,
      "size": 310.6829,
      "equity_after": 333.8574
    },
    {
      "pair": "ALTHEA/USD",
      "entry": 0.079,
      "exit": 0.0853,
      "pnl": 23.1745,
      "pnl_pct": 7.4592,
      "reason": "PROFIT TARGET",
      "bars": 7,
      "entry_bar": 556,
      "exit_bar": 563,
      "size": 310.6829,
      "equity_after": 333.8574
    },
    {
      "pair": "G/USD",
      "entry": 0.0049,
      "exit": 0.0048,
      "pnl": -5.2268,
      "pnl_pct": -1.9303,
      "reason": "TIME MAX",
      "bars": 20,
      "entry_bar": 545,
      "exit_bar": 565,
      "size": 270.7834,
      "equity_after": 265.5566
    },
    {
      "pair": "BAND/USD",
      "entry": 0.3589,
      "exit": 0.341,
      "pnl": -18.3855,
      "pnl_pct": -5.507,
      "reason": "FIXED STOP",
      "bars": 8,
      "entry_bar": 558,
      "exit_bar": 566,
      "size": 333.8574,
      "equity_after": 315.4718
    },
    {
      "pair": "STRK/USD",
      "entry": 0.0872,
      "exit": 0.0828,
      "pnl": -14.6242,
      "pnl_pct": -5.507,
      "reason": "FIXED STOP",
      "bars": 1,
      "entry_bar": 565,
      "exit_bar": 566,
      "size": 265.5566,
      "equity_after": 566.4042
    },
    {
      "pair": "GRIFFAIN/USD",
      "entry": 0.0194,
      "exit": 0.0184,
      "pnl": -15.5959,
      "pnl_pct": -5.507,
      "reason": "FIXED STOP",
      "bars": 1,
      "entry_bar": 566,
      "exit_bar": 567,
      "size": 283.2021,
      "equity_after": 267.6062
    },
    {
      "pair": "WOO/USD",
      "entry": 0.0309,
      "exit": 0.0293,
      "pnl": -15.5959,
      "pnl_pct": -5.507,
      "reason": "FIXED STOP",
      "bars": 1,
      "entry_bar": 566,
      "exit_bar": 567,
      "size": 283.2021,
      "equity_after": 535.2123
    },
    {
      "pair": "SDN/USD",
      "entry": 0.0236,
      "exit": 0.0255,
      "pnl": 19.9613,
      "pnl_pct": 7.4592,
      "reason": "PROFIT TARGET",
      "bars": 1,
      "entry_bar": 567,
      "exit_bar": 568,
      "size": 267.6062,
      "equity_after": 287.5674
    },
    {
      "pair": "BNC/USD",
      "entry": 0.0839,
      "exit": 0.0797,
      "pnl": -18.3855,
      "pnl_pct": -5.507,
      "reason": "FIXED STOP",
      "bars": 8,
      "entry_bar": 563,
      "exit_bar": 571,
      "size": 333.8574,
      "equity_after": 315.4718
    },
    {
      "pair": "BTR/USD",
      "entry": 0.0819,
      "exit": 0.0778,
      "pnl": -17.373,
      "pnl_pct": -5.507,
      "reason": "FIXED STOP",
      "bars": 1,
      "entry_bar": 571,
      "exit_bar": 572,
      "size": 315.4718,
      "equity_after": 298.0988
    },
    {
      "pair": "TEA/USD",
      "entry": 0.027,
      "exit": 0.027,
      "pnl": -1.3916,
      "pnl_pct": -0.52,
      "reason": "TIME MAX",
      "bars": 20,
      "entry_bar": 567,
      "exit_bar": 587,
      "size": 267.6062,
      "equity_after": 266.2146
    },
    {
      "pair": "MXNB/USD",
      "entry": 0.0568,
      "exit": 0.057,
      "pnl": -0.2325,
      "pnl_pct": -0.0808,
      "reason": "TIME MAX",
      "bars": 20,
      "entry_bar": 568,
      "exit_bar": 588,
      "size": 287.5674,
      "equity_after": 287.335
    },
    {
      "pair": "M/USD",
      "entry": 1.5845,
      "exit": 1.5999,
      "pnl": 1.3378,
      "pnl_pct": 0.4488,
      "reason": "TIME MAX",
      "bars": 20,
      "entry_bar": 572,
      "exit_bar": 592,
      "size": 298.0988,
      "equity_after": 299.4366
    },
    {
      "pair": "MUBARAK/USD",
      "entry": 0.0204,
      "exit": 0.0221,
      "pnl": 21.4329,
      "pnl_pct": 7.4592,
      "reason": "PROFIT TARGET",
      "bars": 6,
      "entry_bar": 588,
      "exit_bar": 594,
      "size": 287.335,
      "equity_after": 308.7678
    },
    {
      "pair": "ELX/USD",
      "entry": 0.0026,
      "exit": 0.0028,
      "pnl": 11.5158,
      "pnl_pct": 7.4592,
      "reason": "PROFIT TARGET",
      "bars": 1,
      "entry_bar": 594,
      "exit_bar": 595,
      "size": 154.3839,
      "equity_after": 165.8997
    },
    {
      "pair": "NYM/USD",
      "entry": 0.0303,
      "exit": 0.0327,
      "pnl": 12.3748,
      "pnl_pct": 7.4592,
      "reason": "PROFIT TARGET",
      "bars": 1,
      "entry_bar": 595,
      "exit_bar": 596,
      "size": 165.8997,
      "equity_after": 178.2745
    },
    {
      "pair": "CAMP/USD",
      "entry": 0.0071,
      "exit": 0.0077,
      "pnl": 22.3356,
      "pnl_pct": 7.4592,
      "reason": "PROFIT TARGET",
      "bars": 6,
      "entry_bar": 592,
      "exit_bar": 598,
      "size": 299.4366,
      "equity_after": 321.7722
    },
    {
      "pair": "XRT/USD",
      "entry": 1.045,
      "exit": 0.9927,
      "pnl": -9.8176,
      "pnl_pct": -5.507,
      "reason": "FIXED STOP",
      "bars": 2,
      "entry_bar": 596,
      "exit_bar": 598,
      "size": 178.2745,
      "equity_after": 490.2291
    },
    {
      "pair": "ES/USD",
      "entry": 0.1562,
      "exit": 0.1484,
      "pnl": -8.5019,
      "pnl_pct": -5.507,
      "reason": "FIXED STOP",
      "bars": 9,
      "entry_bar": 594,
      "exit_bar": 603,
      "size": 154.3839,
      "equity_after": 145.882
    },
    {
      "pair": "ZEUS/USD",
      "entry": 0.0131,
      "exit": 0.0124,
      "pnl": -13.4985,
      "pnl_pct": -5.507,
      "reason": "FIXED STOP",
      "bars": 8,
      "entry_bar": 598,
      "exit_bar": 606,
      "size": 245.1146,
      "equity_after": 231.6161
    },
    {
      "pair": "NIL/USD",
      "entry": 0.074,
      "exit": 0.0703,
      "pnl": -8.0337,
      "pnl_pct": -5.507,
      "reason": "FIXED STOP",
      "bars": 4,
      "entry_bar": 603,
      "exit_bar": 607,
      "size": 145.882,
      "equity_after": 137.8483
    },
    {
      "pair": "JTO/USD",
      "entry": 0.3409,
      "exit": 0.3239,
      "pnl": -12.7551,
      "pnl_pct": -5.507,
      "reason": "FIXED STOP",
      "bars": 1,
      "entry_bar": 606,
      "exit_bar": 607,
      "size": 231.6161,
      "equity_after": 356.7093
    },
    {
      "pair": "TERM/USD",
      "entry": 0.607,
      "exit": 0.607,
      "pnl": -1.2746,
      "pnl_pct": -0.52,
      "reason": "TIME MAX",
      "bars": 20,
      "entry_bar": 598,
      "exit_bar": 618,
      "size": 245.1146,
      "equity_after": 243.84
    },
    {
      "pair": "XTER/USD",
      "entry": 0.029,
      "exit": 0.0275,
      "pnl": -9.822,
      "pnl_pct": -5.507,
      "reason": "FIXED STOP",
      "bars": 13,
      "entry_bar": 607,
      "exit_bar": 620,
      "size": 178.3546,
      "equity_after": 168.5326
    },
    {
      "pair": "XAUT/USD",
      "entry": 5053.9,
      "exit": 5458.212,
      "pnl": 13.3038,
      "pnl_pct": 7.4592,
      "reason": "PROFIT TARGET",
      "bars": 19,
      "entry_bar": 607,
      "exit_bar": 626,
      "size": 178.3546,
      "equity_after": 191.6585
    },
    {
      "pair": "XYO/USD",
      "entry": 0.0056,
      "exit": 0.0054,
      "pnl": -13.4283,
      "pnl_pct": -5.507,
      "reason": "FIXED STOP",
      "bars": 12,
      "entry_bar": 618,
      "exit_bar": 630,
      "size": 243.84,
      "equity_after": 230.4117
    },
    {
      "pair": "HONEY/USD",
      "entry": 0.0057,
      "exit": 0.0054,
      "pnl": -12.6888,
      "pnl_pct": -5.507,
      "reason": "FIXED STOP",
      "bars": 1,
      "entry_bar": 630,
      "exit_bar": 631,
      "size": 230.4117,
      "equity_after": 217.7229
    },
    {
      "pair": "BLZ/USD",
      "entry": 0.0176,
      "exit": 0.0167,
      "pnl": -11.99,
      "pnl_pct": -5.507,
      "reason": "FIXED STOP",
      "bars": 1,
      "entry_bar": 631,
      "exit_bar": 632,
      "size": 217.7229,
      "equity_after": 205.7329
    },
    {
      "pair": "MIRROR/USD",
      "entry": 0.0013,
      "exit": 0.0014,
      "pnl": 12.5712,
      "pnl_pct": 7.4592,
      "reason": "PROFIT TARGET",
      "bars": 16,
      "entry_bar": 620,
      "exit_bar": 636,
      "size": 168.5326,
      "equity_after": 181.1038
    },
    {
      "pair": "ICNT/USD",
      "entry": 0.4049,
      "exit": 0.3847,
      "pnl": -11.3297,
      "pnl_pct": -5.507,
      "reason": "FIXED STOP",
      "bars": 8,
      "entry_bar": 632,
      "exit_bar": 640,
      "size": 205.7329,
      "equity_after": 194.4032
    },
    {
      "pair": "UNFI/USD",
      "entry": 0.0955,
      "exit": 0.0907,
      "pnl": -10.5546,
      "pnl_pct": -5.507,
      "reason": "FIXED STOP",
      "bars": 16,
      "entry_bar": 626,
      "exit_bar": 642,
      "size": 191.6585,
      "equity_after": 181.1038
    },
    {
      "pair": "SKY/USD",
      "entry": 0.0648,
      "exit": 0.0616,
      "pnl": -9.9734,
      "pnl_pct": -5.507,
      "reason": "FIXED STOP",
      "bars": 6,
      "entry_bar": 636,
      "exit_bar": 642,
      "size": 181.1038,
      "equity_after": 352.2343
    },
    {
      "pair": "OMNI/USD",
      "entry": 1.147,
      "exit": 1.0897,
      "pnl": -9.6988,
      "pnl_pct": -5.507,
      "reason": "FIXED STOP",
      "bars": 2,
      "entry_bar": 644,
      "exit_bar": 646,
      "size": 176.1171,
      "equity_after": 166.4184
    },
    {
      "pair": "ANIME/USD",
      "entry": 0.0061,
      "exit": 0.0058,
      "pnl": -10.7058,
      "pnl_pct": -5.507,
      "reason": "FIXED STOP",
      "bars": 6,
      "entry_bar": 641,
      "exit_bar": 647,
      "size": 194.4032,
      "equity_after": 350.1158
    },
    {
      "pair": "LMWR/USD",
      "entry": 0.0325,
      "exit": 0.0309,
      "pnl": -9.6404,
      "pnl_pct": -5.507,
      "reason": "FIXED STOP",
      "bars": 1,
      "entry_bar": 649,
      "exit_bar": 650,
      "size": 175.0579,
      "equity_after": 340.4754
    },
    {
      "pair": "SPICE/USD",
      "entry": 0.0,
      "exit": 0.0,
      "pnl": -9.375,
      "pnl_pct": -5.507,
      "reason": "FIXED STOP",
      "bars": 1,
      "entry_bar": 651,
      "exit_bar": 652,
      "size": 170.2377,
      "equity_after": 160.8627
    },
    {
      "pair": "WMTX/USD",
      "entry": 0.0755,
      "exit": 0.0718,
      "pnl": -9.375,
      "pnl_pct": -5.507,
      "reason": "FIXED STOP",
      "bars": 1,
      "entry_bar": 651,
      "exit_bar": 652,
      "size": 170.2377,
      "equity_after": 321.7254
    },
    {
      "pair": "PUPS/USD",
      "entry": 0.002,
      "exit": 0.0019,
      "pnl": -8.8587,
      "pnl_pct": -5.507,
      "reason": "FIXED STOP",
      "bars": 1,
      "entry_bar": 652,
      "exit_bar": 653,
      "size": 160.8627,
      "equity_after": 152.004
    },
    {
      "pair": "ARC/USD",
      "entry": 0.0451,
      "exit": 0.0487,
      "pnl": 11.3383,
      "pnl_pct": 7.4592,
      "reason": "PROFIT TARGET",
      "bars": 2,
      "entry_bar": 653,
      "exit_bar": 655,
      "size": 152.004,
      "equity_after": 163.3423
    },
    {
      "pair": "AB/USD",
      "entry": 0.0028,
      "exit": 0.0027,
      "pnl": -5.4135,
      "pnl_pct": -3.0738,
      "reason": "TIME MAX",
      "bars": 20,
      "entry_bar": 644,
      "exit_bar": 664,
      "size": 176.1171,
      "equity_after": 170.7037
    },
    {
      "pair": "PARTI/USD",
      "entry": 0.0764,
      "exit": 0.0825,
      "pnl": 11.9991,
      "pnl_pct": 7.4592,
      "reason": "PROFIT TARGET",
      "bars": 14,
      "entry_bar": 652,
      "exit_bar": 666,
      "size": 160.8627,
      "equity_after": 172.8618
    },
    {
      "pair": "BLUR/USD",
      "entry": 0.0232,
      "exit": 0.022,
      "pnl": -9.4007,
      "pnl_pct": -5.507,
      "reason": "FIXED STOP",
      "bars": 2,
      "entry_bar": 664,
      "exit_bar": 666,
      "size": 170.7037,
      "equity_after": 334.1648
    },
    {
      "pair": "T/USD",
      "entry": 0.0079,
      "exit": 0.0075,
      "pnl": -8.9953,
      "pnl_pct": -5.507,
      "reason": "FIXED STOP",
      "bars": 15,
      "entry_bar": 655,
      "exit_bar": 670,
      "size": 163.3423,
      "equity_after": 154.347
    },
    {
      "pair": "GNO/USD",
      "entry": 114.09,
      "exit": 108.3855,
      "pnl": -9.2012,
      "pnl_pct": -5.507,
      "reason": "FIXED STOP",
      "bars": 4,
      "entry_bar": 666,
      "exit_bar": 670,
      "size": 167.0824,
      "equity_after": 312.2282
    },
    {
      "pair": "TREE/USD",
      "entry": 0.0728,
      "exit": 0.0692,
      "pnl": -8.5972,
      "pnl_pct": -5.507,
      "reason": "FIXED STOP",
      "bars": 1,
      "entry_bar": 670,
      "exit_bar": 671,
      "size": 156.1141,
      "equity_after": 147.5169
    },
    {
      "pair": "NOT/USD",
      "entry": 0.0004,
      "exit": 0.0004,
      "pnl": -9.2012,
      "pnl_pct": -5.507,
      "reason": "FIXED STOP",
      "bars": 6,
      "entry_bar": 666,
      "exit_bar": 672,
      "size": 167.0824,
      "equity_after": 157.8812
    },
    {
      "pair": "ES/USD",
      "entry": 0.1306,
      "exit": 0.1241,
      "pnl": -8.5972,
      "pnl_pct": -5.507,
      "reason": "FIXED STOP",
      "bars": 2,
      "entry_bar": 670,
      "exit_bar": 672,
      "size": 156.1141,
      "equity_after": 305.398
    },
    {
      "pair": "C98/USD",
      "entry": 0.0275,
      "exit": 0.0297,
      "pnl": 11.0036,
      "pnl_pct": 7.4592,
      "reason": "PROFIT TARGET",
      "bars": 1,
      "entry_bar": 671,
      "exit_bar": 672,
      "size": 147.5169,
      "equity_after": 463.9185
    },
    {
      "pair": "SAMO/USD",
      "entry": 0.0005,
      "exit": 0.0005,
      "pnl": -8.516,
      "pnl_pct": -5.507,
      "reason": "FIXED STOP",
      "bars": 1,
      "entry_bar": 672,
      "exit_bar": 673,
      "size": 154.6395,
      "equity_after": 146.1235
    },
    {
      "pair": "KEY/USD",
      "entry": 0.0002,
      "exit": 0.0002,
      "pnl": -8.516,
      "pnl_pct": -5.507,
      "reason": "FIXED STOP",
      "bars": 1,
      "entry_bar": 672,
      "exit_bar": 673,
      "size": 154.6395,
      "equity_after": 292.247
    },
    {
      "pair": "TEER/USD",
      "entry": 0.0153,
      "exit": 0.0145,
      "pnl": -8.516,
      "pnl_pct": -5.507,
      "reason": "FIXED STOP",
      "bars": 2,
      "entry_bar": 672,
      "exit_bar": 674,
      "size": 154.6395,
      "equity_after": 146.1235
    },
    {
      "pair": "AEVO/USD",
      "entry": 0.0297,
      "exit": 0.0282,
      "pnl": -8.047,
      "pnl_pct": -5.507,
      "reason": "FIXED STOP",
      "bars": 2,
      "entry_bar": 673,
      "exit_bar": 675,
      "size": 146.1235,
      "equity_after": 138.0765
    },
    {
      "pair": "TERM/USD",
      "entry": 0.6,
      "exit": 0.57,
      "pnl": -8.047,
      "pnl_pct": -5.507,
      "reason": "FIXED STOP",
      "bars": 4,
      "entry_bar": 673,
      "exit_bar": 677,
      "size": 146.1235,
      "equity_after": 138.0765
    },
    {
      "pair": "M/USD",
      "entry": 1.5011,
      "exit": 1.6212,
      "pnl": 10.2994,
      "pnl_pct": 7.4592,
      "reason": "PROFIT TARGET",
      "bars": 4,
      "entry_bar": 675,
      "exit_bar": 679,
      "size": 138.0765,
      "equity_after": 148.3759
    },
    {
      "pair": "SIDEKICK/USD",
      "entry": 0.0035,
      "exit": 0.0033,
      "pnl": -7.6039,
      "pnl_pct": -5.507,
      "reason": "FIXED STOP",
      "bars": 1,
      "entry_bar": 678,
      "exit_bar": 679,
      "size": 138.0765,
      "equity_after": 278.8485
    },
    {
      "pair": "ZIG/USD",
      "entry": 0.0399,
      "exit": 0.0431,
      "pnl": 10.3999,
      "pnl_pct": 7.4592,
      "reason": "PROFIT TARGET",
      "bars": 4,
      "entry_bar": 679,
      "exit_bar": 683,
      "size": 139.4242,
      "equity_after": 149.8242
    },
    {
      "pair": "LMWR/USD",
      "entry": 0.0331,
      "exit": 0.0314,
      "pnl": -7.6781,
      "pnl_pct": -5.507,
      "reason": "FIXED STOP",
      "bars": 14,
      "entry_bar": 679,
      "exit_bar": 693,
      "size": 139.4242,
      "equity_after": 131.7462
    },
    {
      "pair": "KET/USD",
      "entry": 0.0027,
      "exit": 0.0026,
      "pnl": -2.4184,
      "pnl_pct": -5.507,
      "reason": "FIXED STOP",
      "bars": 1,
      "entry_bar": 693,
      "exit_bar": 694,
      "size": 43.9154,
      "equity_after": 41.497
    },
    {
      "pair": "ICX/USD",
      "entry": 0.0437,
      "exit": 0.0415,
      "pnl": -2.4184,
      "pnl_pct": -5.507,
      "reason": "FIXED STOP",
      "bars": 2,
      "entry_bar": 693,
      "exit_bar": 695,
      "size": 43.9154,
      "equity_after": 41.497
    },
    {
      "pair": "AXS/USD",
      "entry": 1.5,
      "exit": 1.425,
      "pnl": -2.4184,
      "pnl_pct": -5.507,
      "reason": "FIXED STOP",
      "bars": 3,
      "entry_bar": 693,
      "exit_bar": 696,
      "size": 43.9154,
      "equity_after": 41.497
    },
    {
      "pair": "SONIC/USD",
      "entry": 0.0406,
      "exit": 0.0439,
      "pnl": 3.0953,
      "pnl_pct": 7.4592,
      "reason": "PROFIT TARGET",
      "bars": 2,
      "entry_bar": 694,
      "exit_bar": 696,
      "size": 41.497,
      "equity_after": 86.0893
    },
    {
      "pair": "Q/USD",
      "entry": 0.0184,
      "exit": 0.0199,
      "pnl": 3.0953,
      "pnl_pct": 7.4592,
      "reason": "PROFIT TARGET",
      "bars": 3,
      "entry_bar": 695,
      "exit_bar": 698,
      "size": 41.497,
      "equity_after": 44.5923
    },
    {
      "pair": "REPV2/USD",
      "entry": 0.693,
      "exit": 0.7484,
      "pnl": 3.2108,
      "pnl_pct": 7.4592,
      "reason": "PROFIT TARGET",
      "bars": 3,
      "entry_bar": 696,
      "exit_bar": 699,
      "size": 43.0446,
      "equity_after": 46.2554
    },
    {
      "pair": "BTT/USD",
      "entry": 0.0,
      "exit": 0.0,
      "pnl": -2.5473,
      "pnl_pct": -5.507,
      "reason": "FIXED STOP",
      "bars": 5,
      "entry_bar": 699,
      "exit_bar": 704,
      "size": 46.2554,
      "equity_after": 43.7081
    },
    {
      "pair": "ZRO/USD",
      "entry": 1.801,
      "exit": 1.9451,
      "pnl": 3.2603,
      "pnl_pct": 7.4592,
      "reason": "PROFIT TARGET",
      "bars": 1,
      "entry_bar": 704,
      "exit_bar": 705,
      "size": 43.7081,
      "equity_after": 46.9684
    },
    {
      "pair": "CFG/USD",
      "entry": 0.0871,
      "exit": 0.0827,
      "pnl": -2.4557,
      "pnl_pct": -5.507,
      "reason": "FIXED STOP",
      "bars": 8,
      "entry_bar": 698,
      "exit_bar": 706,
      "size": 44.5923,
      "equity_after": 42.1366
    },
    {
      "pair": "CYBER/USD",
      "entry": 0.535,
      "exit": 0.5082,
      "pnl": -2.5866,
      "pnl_pct": -5.507,
      "reason": "FIXED STOP",
      "bars": 1,
      "entry_bar": 705,
      "exit_bar": 706,
      "size": 46.9684,
      "equity_after": 86.5185
    },
    {
      "pair": "SWARMS/USD",
      "entry": 0.0071,
      "exit": 0.0067,
      "pnl": -2.3705,
      "pnl_pct": -5.507,
      "reason": "FIXED STOP",
      "bars": 11,
      "entry_bar": 696,
      "exit_bar": 707,
      "size": 43.0446,
      "equity_after": 83.9334
    },
    {
      "pair": "INIT/USD",
      "entry": 0.0675,
      "exit": 0.0729,
      "pnl": 3.2268,
      "pnl_pct": 7.4592,
      "reason": "PROFIT TARGET",
      "bars": 1,
      "entry_bar": 706,
      "exit_bar": 707,
      "size": 43.2592,
      "equity_after": 130.4194
    },
    {
      "pair": "LINEA/USD",
      "entry": 0.0032,
      "exit": 0.0034,
      "pnl": 3.2427,
      "pnl_pct": 7.4592,
      "reason": "PROFIT TARGET",
      "bars": 1,
      "entry_bar": 707,
      "exit_bar": 708,
      "size": 43.4731,
      "equity_after": 90.189
    },
    {
      "pair": "T/USD",
      "entry": 0.007,
      "exit": 0.0072,
      "pnl": 0.6991,
      "pnl_pct": 1.6082,
      "reason": "END",
      "bars": 13,
      "entry_bar": 707,
      "exit_bar": 720,
      "size": 43.4731,
      "equity_after": 44.1723
    },
    {
      "pair": "PROMPT/USD",
      "entry": 0.0474,
      "exit": 0.0469,
      "pnl": -0.7093,
      "pnl_pct": -1.573,
      "reason": "END",
      "bars": 12,
      "entry_bar": 708,
      "exit_bar": 720,
      "size": 45.0945,
      "equity_after": 88.5574
    },
    {
      "pair": "ZK/USD",
      "entry": 0.0215,
      "exit": 0.022,
      "pnl": 0.6212,
      "pnl_pct": 1.3776,
      "reason": "END",
      "bars": 12,
      "entry_bar": 708,
      "exit_bar": 720,
      "size": 45.0945,
      "equity_after": 134.2732
    }
  ]
}