{
  "generated": "2026-02-15 00:50 CET",
  "label_a": "RESEARCH_ALL",
  "label_b": "LIVE_CURRENT",
  "metrics_a": {
    "universe_mode": "all",
    "coin_count": 2086,
    "dataset_hash": "a68399c0da2e",
    "configs": {
      "C1_TPSL_RSI45": {
        "trades": 45,
        "pnl": 528.52,
        "wr": 51.1,
        "dd": 40.8,
        "pf": 1.14,
        "wf_label": "3/5",
        "wf_pass": 3,
        "wf_go": false,
        "fric_go_pnl": -333.86,
        "fric_go": false,
        "mc_ruin": 37.5,
        "mc_p95_dd": 62.6,
        "mc_win_pct": 100.0,
        "mc_go": false,
        "jitter_pct": 26.0,
        "jitter_go": false,
        "univ_n_pos": 2,
        "univ_go": true,
        "top1_coin": "MF/USD",
        "top1_share": 0.125,
        "top3_share": 0.273,
        "notop_pnl": -23.8,
        "verdict": "NO-GO",
        "fails": [
          "Friction",
          "MC",
          "Jitter"
        ]
      }
    }
  },
  "metrics_b": {
    "universe_mode": "all",
    "coin_count": 523,
    "dataset_hash": "3b1dba2eeb4d",
    "configs": {
      "C1_TPSL_RSI45": {
        "trades": 30,
        "pnl": 3745.5,
        "wr": 70.0,
        "dd": 27.9,
        "pf": 3.31,
        "wf_label": "4/5",
        "wf_pass": 4,
        "wf_go": true,
        "fric_go_pnl": 2369.98,
        "fric_go": true,
        "mc_ruin": 0.0,
        "mc_p95_dd": 31.5,
        "mc_win_pct": 100.0,
        "mc_go": true,
        "jitter_pct": 98.0,
        "jitter_go": true,
        "univ_n_pos": 4,
        "univ_go": true,
        "top1_coin": "MF/USD",
        "top1_share": 0.169,
        "top3_share": 0.43,
        "notop_pnl": 2837.97,
        "verdict": "GO",
        "fails": []
      }
    }
  }
}