{
  "metadata": {
    "run_id": "sweep_v1_018_sv1c06_hh1_sw5_tol2.0_rsi45_57a688e3",
    "config_id": "sweep_v1_018_sv1c06_hh1_sw5_tol2.0_rsi45",
    "hypothesis_id": "SV1-C06",
    "hypothesis_name": "TrendPullback HH1 Swing5 Tol2.0 RSI45",
    "family": "TrendPullback",
    "category": "trend_following",
    "dataset_id": "ohlcv_4h_kraken_spot_usd_526",
    "universe_id": "sweep_v1_487coins_min360bars",
    "exchange": "kraken",
    "fee_model": "kraken_spot_26bps",
    "fee_bps": 26.0,
    "n_coins": 487,
    "elapsed_s": 0.09,
    "timestamp": "2026-02-26T05:04:45.467072+00:00",
    "git_hash": "57a688e3",
    "engine": "sprint3.engine (exit_mode=dc) + sweep_v1 indicators",
    "exit_mode": "dc",
    "strict_pf": 1.05,
    "research_pf": 1.0,
    "compat_score": {
      "total_entries": 18313,
      "passing_entries": 18313,
      "avg_composite": 0.529,
      "median_composite": 0.5184,
      "top_quartile_composite": 0.765,
      "avg_features": {
        "dc_distance": 0.4751,
        "bb_distance": 0.5055,
        "rsi_headroom": 0.649,
        "channel_pos": 0.712,
        "atr_regime": 0.5469,
        "wick_structure": 0.5019,
        "volume_surge": 0.1357
      },
      "elapsed_s": 0.21,
      "hard_pass": true
    }
  },
  "params": {
    "rsi_max": 45,
    "min_hh_hl": 1,
    "swing_window": 5,
    "pullback_tol": 2.0,
    "max_pos": 3,
    "max_stop_pct": 15.0,
    "time_max_bars": 15,
    "rsi_recovery": true,
    "rsi_rec_target": 45,
    "rsi_rec_min_bars": 2
  },
  "summary": {
    "trades": 259,
    "wr": 59.07,
    "pnl": -367.57,
    "final_equity": 1632.43,
    "pf": 1.0874,
    "dd": 55.88,
    "broke": false,
    "ev_per_trade": -1.42
  },
  "exit_classes": {
    "A": {
      "RSI RECOVERY": {
        "count": 149,
        "pnl": 4894.087917745088,
        "wins": 121
      },
      "BB TARGET": {
        "count": 18,
        "pnl": 1176.1174695754894,
        "wins": 17
      },
      "DC TARGET": {
        "count": 13,
        "pnl": 1122.3646920434662,
        "wins": 12
      }
    },
    "B": {
      "TIME MAX": {
        "count": 40,
        "pnl": -2097.104124424797,
        "wins": 0
      },
      "FIXED STOP": {
        "count": 36,
        "pnl": -4512.71375404349,
        "wins": 0
      },
      "END": {
        "count": 3,
        "pnl": 19.737309041727517,
        "wins": 3
      }
    }
  },
  "edge_decomposition": {
    "class_a_share": 0.9973,
    "class_a_pnl": 7192.57,
    "class_b_pnl": -6590.08,
    "stopout_ratio": 0.139,
    "breakeven_fee_bps": 41.2,
    "research_grade": "STRONG_LEAD",
    "research_notes": [
      "STRONG LEAD: PF=1.09, Class A share=100%, stopout ratio=14%",
      "Best exit: RSI RECOVERY ($4894, 149 trades, 81% WR)",
      "Worst exit: FIXED STOP ($-4513, 36 trades)",
      "Breakeven fee: 41.2 bps per side",
      "LOW STOPOUT: 14% -- entries have good geometric placement"
    ]
  },
  "trade_count": 259,
  "trades": [
    {
      "pair": "RHEA/USD",
      "entry": 0.02299,
      "exit": 0.02341,
      "pnl": 8.6809,
      "pnl_pct": 1.3021,
      "reason": "RSI RECOVERY",
      "bars": 2,
      "entry_bar": 50,
      "exit_bar": 52,
      "size": 666.6667,
      "equity_after": 675.3475
    },
    {
      "pair": "LAVA/USD",
      "entry": 0.14419,
      "exit": 0.1502,
      "pnl": 24.2485,
      "pnl_pct": 3.6373,
      "reason": "RSI RECOVERY",
      "bars": 11,
      "entry_bar": 50,
      "exit_bar": 61,
      "size": 666.6667,
      "equity_after": 690.9152
    },
    {
      "pair": "BLUE/USD",
      "entry": 0.04542,
      "exit": 0.04735,
      "pnl": 25.1106,
      "pnl_pct": 3.7182,
      "reason": "RSI RECOVERY",
      "bars": 10,
      "entry_bar": 52,
      "exit_bar": 62,
      "size": 675.3475,
      "equity_after": 700.4582
    },
    {
      "pair": "PRIME/USD",
      "entry": 1.195,
      "exit": 1.22,
      "pnl": 10.824,
      "pnl_pct": 1.5666,
      "reason": "BB TARGET",
      "bars": 1,
      "entry_bar": 61,
      "exit_bar": 62,
      "size": 690.9152,
      "equity_after": 1402.1973
    },
    {
      "pair": "CORN/USD",
      "entry": 0.07904,
      "exit": 0.07799,
      "pnl": -12.2999,
      "pnl_pct": -1.845,
      "reason": "RSI RECOVERY",
      "bars": 13,
      "entry_bar": 50,
      "exit_bar": 63,
      "size": 666.6667,
      "equity_after": 654.3668
    },
    {
      "pair": "AIR/USD",
      "entry": 0.00208,
      "exit": 0.00257,
      "pnl": 161.0875,
      "pnl_pct": 22.9764,
      "reason": "DC TARGET",
      "bars": 1,
      "entry_bar": 62,
      "exit_bar": 63,
      "size": 701.0987,
      "equity_after": 1516.5529
    },
    {
      "pair": "RVV/USD",
      "entry": 0.004068,
      "exit": 0.004349,
      "pnl": 44.6573,
      "pnl_pct": 6.3696,
      "reason": "DC TARGET",
      "bars": 7,
      "entry_bar": 62,
      "exit_bar": 69,
      "size": 701.0987,
      "equity_after": 745.7559
    },
    {
      "pair": "M/USD",
      "entry": 2.0931,
      "exit": 2.18604,
      "pnl": 29.6392,
      "pnl_pct": 3.9088,
      "reason": "DC TARGET",
      "bars": 7,
      "entry_bar": 63,
      "exit_bar": 70,
      "size": 758.2765,
      "equity_after": 787.9157
    },
    {
      "pair": "ENJ/USD",
      "entry": 0.0433,
      "exit": 0.0442,
      "pnl": 11.5825,
      "pnl_pct": 1.5531,
      "reason": "RSI RECOVERY",
      "bars": 2,
      "entry_bar": 69,
      "exit_bar": 71,
      "size": 745.7559,
      "equity_after": 757.3384
    },
    {
      "pair": "VELVET/USD",
      "entry": 0.2091,
      "exit": 0.197,
      "pnl": -47.7082,
      "pnl_pct": -6.2917,
      "reason": "TIME MAX",
      "bars": 15,
      "entry_bar": 63,
      "exit_bar": 78,
      "size": 758.2765,
      "equity_after": 710.5683
    },
    {
      "pair": "FF/USD",
      "entry": 0.15164,
      "exit": 0.128894,
      "pnl": -117.2436,
      "pnl_pct": -15.481,
      "reason": "FIXED STOP",
      "bars": 13,
      "entry_bar": 71,
      "exit_bar": 84,
      "size": 757.3384,
      "equity_after": 640.0948
    },
    {
      "pair": "TRAC/USD",
      "entry": 0.716,
      "exit": 0.6086,
      "pnl": -121.9772,
      "pnl_pct": -15.481,
      "reason": "FIXED STOP",
      "bars": 15,
      "entry_bar": 70,
      "exit_bar": 85,
      "size": 787.9157,
      "equity_after": 665.9384
    },
    {
      "pair": "SOSO/USD",
      "entry": 0.7712,
      "exit": 0.8028,
      "pnl": 22.8313,
      "pnl_pct": 3.5669,
      "reason": "RSI RECOVERY",
      "bars": 8,
      "entry_bar": 84,
      "exit_bar": 92,
      "size": 640.0948,
      "equity_after": 662.9261
    },
    {
      "pair": "FHE/USD",
      "entry": 0.03777,
      "exit": 0.03554,
      "pnl": -45.5389,
      "pnl_pct": -6.4088,
      "reason": "TIME MAX",
      "bars": 15,
      "entry_bar": 78,
      "exit_bar": 93,
      "size": 710.5683,
      "equity_after": 665.0293
    },
    {
      "pair": "BOBA/USD",
      "entry": 0.0629,
      "exit": 0.0646,
      "pnl": 14.4887,
      "pnl_pct": 2.1757,
      "reason": "BB TARGET",
      "bars": 10,
      "entry_bar": 85,
      "exit_bar": 95,
      "size": 665.9384,
      "equity_after": 680.4271
    },
    {
      "pair": "EAT/USD",
      "entry": 0.05156,
      "exit": 0.04994,
      "pnl": -24.2989,
      "pnl_pct": -3.6538,
      "reason": "RSI RECOVERY",
      "bars": 4,
      "entry_bar": 93,
      "exit_bar": 97,
      "size": 665.0293,
      "equity_after": 640.7305
    },
    {
      "pair": "ANLOG/USD",
      "entry": 0.001285,
      "exit": 0.0016,
      "pnl": 158.6374,
      "pnl_pct": 23.9299,
      "reason": "RSI RECOVERY",
      "bars": 8,
      "entry_bar": 92,
      "exit_bar": 100,
      "size": 662.9261,
      "equity_after": 821.5635
    },
    {
      "pair": "CHILLHOUSE/USD",
      "entry": 0.00711,
      "exit": 0.00914,
      "pnl": 179.1297,
      "pnl_pct": 27.9571,
      "reason": "RSI RECOVERY",
      "bars": 6,
      "entry_bar": 97,
      "exit_bar": 103,
      "size": 640.7305,
      "equity_after": 819.8602
    },
    {
      "pair": "EAT/USD",
      "entry": 0.04366,
      "exit": 0.04534,
      "pnl": 27.2022,
      "pnl_pct": 3.3179,
      "reason": "RSI RECOVERY",
      "bars": 6,
      "entry_bar": 103,
      "exit_bar": 109,
      "size": 819.8602,
      "equity_after": 847.0624
    },
    {
      "pair": "DBR/USD",
      "entry": 0.03227,
      "exit": 0.02958,
      "pnl": -60.1106,
      "pnl_pct": -8.8342,
      "reason": "TIME MAX",
      "bars": 15,
      "entry_bar": 95,
      "exit_bar": 110,
      "size": 680.4271,
      "equity_after": 620.3165
    },
    {
      "pair": "XMN/USD",
      "entry": 0.04829,
      "exit": 0.05045,
      "pnl": 32.3807,
      "pnl_pct": 3.9413,
      "reason": "BB TARGET",
      "bars": 11,
      "entry_bar": 100,
      "exit_bar": 111,
      "size": 821.5635,
      "equity_after": 853.9442
    },
    {
      "pair": "UFD/USD",
      "entry": 0.01404,
      "exit": 0.011934,
      "pnl": -131.1337,
      "pnl_pct": -15.481,
      "reason": "FIXED STOP",
      "bars": 4,
      "entry_bar": 109,
      "exit_bar": 113,
      "size": 847.0624,
      "equity_after": 715.9287
    },
    {
      "pair": "EDU/USD",
      "entry": 0.16089,
      "exit": 0.1683,
      "pnl": 29.1645,
      "pnl_pct": 4.0737,
      "reason": "BB TARGET",
      "bars": 1,
      "entry_bar": 113,
      "exit_bar": 114,
      "size": 715.9287,
      "equity_after": 745.0932
    },
    {
      "pair": "KGEN/USD",
      "entry": 0.2642,
      "exit": 0.2623,
      "pnl": -7.6751,
      "pnl_pct": -1.2373,
      "reason": "RSI RECOVERY",
      "bars": 5,
      "entry_bar": 110,
      "exit_bar": 115,
      "size": 620.3165,
      "equity_after": 612.6415
    },
    {
      "pair": "XTER/USD",
      "entry": 0.05614,
      "exit": 0.05791,
      "pnl": 22.4129,
      "pnl_pct": 2.6246,
      "reason": "BB TARGET",
      "bars": 9,
      "entry_bar": 111,
      "exit_bar": 120,
      "size": 853.9442,
      "equity_after": 876.3571
    },
    {
      "pair": "SYRUP/USD",
      "entry": 0.37243,
      "exit": 0.39817,
      "pnl": 47.4877,
      "pnl_pct": 6.3734,
      "reason": "RSI RECOVERY",
      "bars": 7,
      "entry_bar": 114,
      "exit_bar": 121,
      "size": 745.0932,
      "equity_after": 792.5809
    },
    {
      "pair": "MOCA/USD",
      "entry": 0.04431,
      "exit": 0.0376635,
      "pnl": -122.6994,
      "pnl_pct": -15.481,
      "reason": "FIXED STOP",
      "bars": 6,
      "entry_bar": 121,
      "exit_bar": 127,
      "size": 792.5809,
      "equity_after": 669.8814
    },
    {
      "pair": "LIT/USD",
      "entry": 0.2074,
      "exit": 0.2214,
      "pnl": 38.0615,
      "pnl_pct": 6.2127,
      "reason": "RSI RECOVERY",
      "bars": 14,
      "entry_bar": 115,
      "exit_bar": 129,
      "size": 612.6415,
      "equity_after": 650.703
    },
    {
      "pair": "BOS/USD",
      "entry": 0.006317,
      "exit": 0.00536945,
      "pnl": -135.6688,
      "pnl_pct": -15.481,
      "reason": "FIXED STOP",
      "bars": 11,
      "entry_bar": 120,
      "exit_bar": 131,
      "size": 876.3571,
      "equity_after": 740.6883
    },
    {
      "pair": "H/USD",
      "entry": 0.11114,
      "exit": 0.20076,
      "pnl": 535.2847,
      "pnl_pct": 79.9074,
      "reason": "BB TARGET",
      "bars": 6,
      "entry_bar": 127,
      "exit_bar": 133,
      "size": 669.8814,
      "equity_after": 1205.1661
    },
    {
      "pair": "ARC/USD",
      "entry": 0.02313,
      "exit": 0.0253,
      "pnl": 65.4573,
      "pnl_pct": 8.8374,
      "reason": "RSI RECOVERY",
      "bars": 6,
      "entry_bar": 131,
      "exit_bar": 137,
      "size": 740.6883,
      "equity_after": 806.1456
    },
    {
      "pair": "BOB/USD",
      "entry": 0.01519,
      "exit": 0.01631,
      "pnl": 82.3623,
      "pnl_pct": 6.8341,
      "reason": "RSI RECOVERY",
      "bars": 4,
      "entry_bar": 133,
      "exit_bar": 137,
      "size": 1205.1661,
      "equity_after": 2093.674
    },
    {
      "pair": "OBOL/USD",
      "entry": 0.0585,
      "exit": 0.05898,
      "pnl": 1.9416,
      "pnl_pct": 0.2984,
      "reason": "RSI RECOVERY",
      "bars": 9,
      "entry_bar": 129,
      "exit_bar": 138,
      "size": 650.703,
      "equity_after": 652.6445
    },
    {
      "pair": "KMNO/USD",
      "entry": 0.05911,
      "exit": 0.06,
      "pnl": 6.4074,
      "pnl_pct": 0.9818,
      "reason": "RSI RECOVERY",
      "bars": 2,
      "entry_bar": 138,
      "exit_bar": 140,
      "size": 652.6445,
      "equity_after": 659.0519
    },
    {
      "pair": "M/USD",
      "entry": 2.37157,
      "exit": 2.4192,
      "pnl": 9.7747,
      "pnl_pct": 1.4832,
      "reason": "RSI RECOVERY",
      "bars": 2,
      "entry_bar": 140,
      "exit_bar": 142,
      "size": 659.0519,
      "equity_after": 668.8266
    },
    {
      "pair": "ZK/USD",
      "entry": 0.05947,
      "exit": 0.06495,
      "pnl": 90.7688,
      "pnl_pct": 8.6708,
      "reason": "RSI RECOVERY",
      "bars": 11,
      "entry_bar": 137,
      "exit_bar": 148,
      "size": 1046.837,
      "equity_after": 1137.6058
    },
    {
      "pair": "RIVER/USD",
      "entry": 2.894,
      "exit": 4.02,
      "pnl": 435.5543,
      "pnl_pct": 38.2869,
      "reason": "DC TARGET",
      "bars": 1,
      "entry_bar": 148,
      "exit_bar": 149,
      "size": 1137.6058,
      "equity_after": 1573.1601
    },
    {
      "pair": "HOLO/USD",
      "entry": 0.0896,
      "exit": 0.07616,
      "pnl": -162.0608,
      "pnl_pct": -15.481,
      "reason": "FIXED STOP",
      "bars": 13,
      "entry_bar": 137,
      "exit_bar": 150,
      "size": 1046.837,
      "equity_after": 884.7762
    },
    {
      "pair": "NOS/USD",
      "entry": 0.339,
      "exit": 0.343,
      "pnl": 4.3933,
      "pnl_pct": 0.6569,
      "reason": "RSI RECOVERY",
      "bars": 11,
      "entry_bar": 142,
      "exit_bar": 153,
      "size": 668.8266,
      "equity_after": 673.22
    },
    {
      "pair": "STORJ/USD",
      "entry": 0.17411,
      "exit": 0.17946,
      "pnl": 22.5156,
      "pnl_pct": 2.5448,
      "reason": "RSI RECOVERY",
      "bars": 5,
      "entry_bar": 150,
      "exit_bar": 155,
      "size": 884.7762,
      "equity_after": 907.2918
    },
    {
      "pair": "ICP/USD",
      "entry": 7.051,
      "exit": 5.99335,
      "pnl": -243.5409,
      "pnl_pct": -15.481,
      "reason": "FIXED STOP",
      "bars": 9,
      "entry_bar": 149,
      "exit_bar": 158,
      "size": 1573.1601,
      "equity_after": 1329.6192
    },
    {
      "pair": "ALT/USD",
      "entry": 0.01609,
      "exit": 0.01718,
      "pnl": 82.9254,
      "pnl_pct": 6.2368,
      "reason": "RSI RECOVERY",
      "bars": 2,
      "entry_bar": 158,
      "exit_bar": 160,
      "size": 1329.6192,
      "equity_after": 1412.5447
    },
    {
      "pair": "IDEX/USD",
      "entry": 0.01851,
      "exit": 0.01691,
      "pnl": -61.5424,
      "pnl_pct": -9.1415,
      "reason": "TIME MAX",
      "bars": 15,
      "entry_bar": 153,
      "exit_bar": 168,
      "size": 673.22,
      "equity_after": 611.6776
    },
    {
      "pair": "BTR/USD",
      "entry": 0.0585,
      "exit": 0.049725,
      "pnl": -218.676,
      "pnl_pct": -15.481,
      "reason": "FIXED STOP",
      "bars": 9,
      "entry_bar": 160,
      "exit_bar": 169,
      "size": 1412.5447,
      "equity_after": 1193.8686
    },
    {
      "pair": "VINE/USD",
      "entry": 0.04003,
      "exit": 0.0340255,
      "pnl": -94.6938,
      "pnl_pct": -15.481,
      "reason": "FIXED STOP",
      "bars": 1,
      "entry_bar": 168,
      "exit_bar": 169,
      "size": 611.6776,
      "equity_after": 1710.8524
    },
    {
      "pair": "BANANAS31/USD",
      "entry": 0.002481,
      "exit": 0.002405,
      "pnl": -32.4386,
      "pnl_pct": -3.5753,
      "reason": "TIME MAX",
      "bars": 15,
      "entry_bar": 155,
      "exit_bar": 170,
      "size": 907.2918,
      "equity_after": 874.8532
    },
    {
      "pair": "MYX/USD",
      "entry": 2.306,
      "exit": 2.453,
      "pnl": 51.0748,
      "pnl_pct": 5.8381,
      "reason": "RSI RECOVERY",
      "bars": 6,
      "entry_bar": 170,
      "exit_bar": 176,
      "size": 874.8532,
      "equity_after": 925.928
    },
    {
      "pair": "STBL/USD",
      "entry": 0.072991,
      "exit": 0.073817,
      "pnl": 5.207,
      "pnl_pct": 0.6087,
      "reason": "RSI RECOVERY",
      "bars": 14,
      "entry_bar": 169,
      "exit_bar": 183,
      "size": 855.4262,
      "equity_after": 860.6332
    },
    {
      "pair": "ACT/USD",
      "entry": 0.01851,
      "exit": 0.01804,
      "pnl": -26.1125,
      "pnl_pct": -3.0526,
      "reason": "TIME MAX",
      "bars": 15,
      "entry_bar": 169,
      "exit_bar": 184,
      "size": 855.4262,
      "equity_after": 829.3137
    },
    {
      "pair": "STRD/USD",
      "entry": 0.0701,
      "exit": 0.0778,
      "pnl": 86.5451,
      "pnl_pct": 10.4357,
      "reason": "RSI RECOVERY",
      "bars": 3,
      "entry_bar": 184,
      "exit_bar": 187,
      "size": 829.3137,
      "equity_after": 915.8588
    },
    {
      "pair": "SKY/USD",
      "entry": 0.05055,
      "exit": 0.05104,
      "pnl": 4.1372,
      "pnl_pct": 0.4468,
      "reason": "RSI RECOVERY",
      "bars": 13,
      "entry_bar": 176,
      "exit_bar": 189,
      "size": 925.928,
      "equity_after": 930.0652
    },
    {
      "pair": "NANO/USD",
      "entry": 0.979279,
      "exit": 1.023981,
      "pnl": 34.7086,
      "pnl_pct": 4.0329,
      "reason": "RSI RECOVERY",
      "bars": 6,
      "entry_bar": 183,
      "exit_bar": 189,
      "size": 860.6332,
      "equity_after": 1825.4071
    },
    {
      "pair": "AB/USD",
      "entry": 0.006916,
      "exit": 0.006898,
      "pnl": -7.1153,
      "pnl_pct": -0.7796,
      "reason": "RSI RECOVERY",
      "bars": 2,
      "entry_bar": 189,
      "exit_bar": 191,
      "size": 912.7035,
      "equity_after": 905.5882
    },
    {
      "pair": "STRD/USD",
      "entry": 0.0698,
      "exit": 0.05933,
      "pnl": -140.1941,
      "pnl_pct": -15.481,
      "reason": "FIXED STOP",
      "bars": 3,
      "entry_bar": 191,
      "exit_bar": 194,
      "size": 905.5882,
      "equity_after": 765.3941
    },
    {
      "pair": "ASTER/USD",
      "entry": 1.17712,
      "exit": 1.19276,
      "pnl": 7.3746,
      "pnl_pct": 0.8052,
      "reason": "RSI RECOVERY",
      "bars": 14,
      "entry_bar": 187,
      "exit_bar": 201,
      "size": 915.8588,
      "equity_after": 923.2334
    },
    {
      "pair": "CAMP/USD",
      "entry": 0.00903,
      "exit": 0.00886,
      "pnl": -21.8841,
      "pnl_pct": -2.3977,
      "reason": "TIME MAX",
      "bars": 15,
      "entry_bar": 189,
      "exit_bar": 204,
      "size": 912.7035,
      "equity_after": 890.8195
    },
    {
      "pair": "FIS/USD",
      "entry": 0.0531,
      "exit": 0.0547,
      "pnl": 22.14,
      "pnl_pct": 2.4853,
      "reason": "RSI RECOVERY",
      "bars": 3,
      "entry_bar": 204,
      "exit_bar": 207,
      "size": 890.8195,
      "equity_after": 912.9594
    },
    {
      "pair": "SYND/USD",
      "entry": 0.1082,
      "exit": 0.1007,
      "pnl": -56.8962,
      "pnl_pct": -7.4336,
      "reason": "TIME MAX",
      "bars": 15,
      "entry_bar": 194,
      "exit_bar": 209,
      "size": 765.3941,
      "equity_after": 708.4979
    },
    {
      "pair": "BIT/USD",
      "entry": 1.0662,
      "exit": 1.1031,
      "pnl": 27.0682,
      "pnl_pct": 2.9319,
      "reason": "RSI RECOVERY",
      "bars": 9,
      "entry_bar": 201,
      "exit_bar": 210,
      "size": 923.2334,
      "equity_after": 950.3016
    },
    {
      "pair": "UXLINK/USD",
      "entry": 0.0119,
      "exit": 0.015,
      "pnl": 241.9724,
      "pnl_pct": 25.4627,
      "reason": "RSI RECOVERY",
      "bars": 6,
      "entry_bar": 210,
      "exit_bar": 216,
      "size": 950.3016,
      "equity_after": 1192.274
    },
    {
      "pair": "CQT/USD",
      "entry": 0.00104,
      "exit": 0.000884,
      "pnl": -141.3353,
      "pnl_pct": -15.481,
      "reason": "FIXED STOP",
      "bars": 10,
      "entry_bar": 207,
      "exit_bar": 217,
      "size": 912.9594,
      "equity_after": 771.6242
    },
    {
      "pair": "BANANAS31/USD",
      "entry": 0.002613,
      "exit": 0.002425,
      "pnl": -54.5266,
      "pnl_pct": -7.6961,
      "reason": "TIME MAX",
      "bars": 15,
      "entry_bar": 209,
      "exit_bar": 224,
      "size": 708.4979,
      "equity_after": 653.9712
    },
    {
      "pair": "SAHARA/USD",
      "entry": 0.07696,
      "exit": 0.079,
      "pnl": 25.3219,
      "pnl_pct": 2.1238,
      "reason": "RSI RECOVERY",
      "bars": 9,
      "entry_bar": 216,
      "exit_bar": 225,
      "size": 1192.274,
      "equity_after": 1217.5959
    },
    {
      "pair": "FF/USD",
      "entry": 0.12227,
      "exit": 0.1263,
      "pnl": 21.354,
      "pnl_pct": 2.7674,
      "reason": "RSI RECOVERY",
      "bars": 12,
      "entry_bar": 217,
      "exit_bar": 229,
      "size": 771.6242,
      "equity_after": 792.9782
    },
    {
      "pair": "CORN/USD",
      "entry": 0.07139,
      "exit": 0.07313,
      "pnl": 15.1536,
      "pnl_pct": 1.911,
      "reason": "RSI RECOVERY",
      "bars": 7,
      "entry_bar": 229,
      "exit_bar": 236,
      "size": 792.9782,
      "equity_after": 808.1319
    },
    {
      "pair": "FOLKS/USD",
      "entry": 21.3908,
      "exit": 18.18218,
      "pnl": -125.1069,
      "pnl_pct": -15.481,
      "reason": "FIXED STOP",
      "bars": 1,
      "entry_bar": 236,
      "exit_bar": 237,
      "size": 808.1319,
      "equity_after": 683.025
    },
    {
      "pair": "STRK/USD",
      "entry": 0.14461,
      "exit": 0.1365,
      "pnl": -39.9812,
      "pnl_pct": -6.1136,
      "reason": "TIME MAX",
      "bars": 15,
      "entry_bar": 224,
      "exit_bar": 239,
      "size": 653.9712,
      "equity_after": 613.99
    },
    {
      "pair": "MERL/USD",
      "entry": 0.3521,
      "exit": 0.32105,
      "pnl": -113.4262,
      "pnl_pct": -9.3156,
      "reason": "TIME MAX",
      "bars": 15,
      "entry_bar": 225,
      "exit_bar": 240,
      "size": 1217.5959,
      "equity_after": 1104.1697
    },
    {
      "pair": "AB/USD",
      "entry": 0.006261,
      "exit": 0.006326,
      "pnl": 3.165,
      "pnl_pct": 0.5155,
      "reason": "RSI RECOVERY",
      "bars": 4,
      "entry_bar": 239,
      "exit_bar": 243,
      "size": 613.99,
      "equity_after": 617.155
    },
    {
      "pair": "DAG/USD",
      "entry": 0.012878,
      "exit": 0.013565,
      "pnl": 53.0091,
      "pnl_pct": 4.8008,
      "reason": "RSI RECOVERY",
      "bars": 3,
      "entry_bar": 240,
      "exit_bar": 243,
      "size": 1104.1697,
      "equity_after": 1774.3337
    },
    {
      "pair": "OBOL/USD",
      "entry": 0.02391,
      "exit": 0.02411,
      "pnl": 2.1467,
      "pnl_pct": 0.3143,
      "reason": "RSI RECOVERY",
      "bars": 7,
      "entry_bar": 237,
      "exit_bar": 244,
      "size": 683.025,
      "equity_after": 685.1717
    },
    {
      "pair": "YALA/USD",
      "entry": 0.0406,
      "exit": 0.03451,
      "pnl": -137.3423,
      "pnl_pct": -15.481,
      "reason": "FIXED STOP",
      "bars": 1,
      "entry_bar": 243,
      "exit_bar": 244,
      "size": 887.1669,
      "equity_after": 1434.9963
    },
    {
      "pair": "RAIIN/USD",
      "entry": 0.00126,
      "exit": 0.00176,
      "pnl": 346.5217,
      "pnl_pct": 39.0594,
      "reason": "RSI RECOVERY",
      "bars": 2,
      "entry_bar": 243,
      "exit_bar": 245,
      "size": 887.1669,
      "equity_after": 1233.6886
    },
    {
      "pair": "NOBODY/USD",
      "entry": 0.01429,
      "exit": 0.01468,
      "pnl": 15.7999,
      "pnl_pct": 2.2021,
      "reason": "RSI RECOVERY",
      "bars": 4,
      "entry_bar": 244,
      "exit_bar": 248,
      "size": 717.4981,
      "equity_after": 733.2981
    },
    {
      "pair": "FOLKS/USD",
      "entry": 7.6543,
      "exit": 6.506155,
      "pnl": -190.9873,
      "pnl_pct": -15.481,
      "reason": "FIXED STOP",
      "bars": 5,
      "entry_bar": 245,
      "exit_bar": 250,
      "size": 1233.6886,
      "equity_after": 1042.7013
    },
    {
      "pair": "CCD/USD",
      "entry": 0.015851,
      "exit": 0.019184,
      "pnl": 146.7455,
      "pnl_pct": 20.4524,
      "reason": "RSI RECOVERY",
      "bars": 7,
      "entry_bar": 244,
      "exit_bar": 251,
      "size": 717.4981,
      "equity_after": 864.2437
    },
    {
      "pair": "BOBA/USD",
      "entry": 0.0453,
      "exit": 0.0453,
      "pnl": -5.422,
      "pnl_pct": -0.52,
      "reason": "RSI RECOVERY",
      "bars": 3,
      "entry_bar": 250,
      "exit_bar": 253,
      "size": 1042.7013,
      "equity_after": 1037.2792
    },
    {
      "pair": "XNAP/USD",
      "entry": 0.00137,
      "exit": 0.0011645,
      "pnl": -160.5812,
      "pnl_pct": -15.481,
      "reason": "FIXED STOP",
      "bars": 5,
      "entry_bar": 253,
      "exit_bar": 258,
      "size": 1037.2792,
      "equity_after": 876.698
    },
    {
      "pair": "SUSHI/USD",
      "entry": 0.396,
      "exit": 0.3841,
      "pnl": -25.7918,
      "pnl_pct": -3.5172,
      "reason": "RSI RECOVERY",
      "bars": 12,
      "entry_bar": 248,
      "exit_bar": 260,
      "size": 733.2981,
      "equity_after": 707.5062
    },
    {
      "pair": "M/USD",
      "entry": 1.24811,
      "exit": 1.3963,
      "pnl": 97.8521,
      "pnl_pct": 11.3223,
      "reason": "RSI RECOVERY",
      "bars": 13,
      "entry_bar": 251,
      "exit_bar": 264,
      "size": 864.2437,
      "equity_after": 962.0958
    },
    {
      "pair": "SAHARA/USD",
      "entry": 0.07818,
      "exit": 0.066453,
      "pnl": -135.7216,
      "pnl_pct": -15.481,
      "reason": "FIXED STOP",
      "bars": 6,
      "entry_bar": 258,
      "exit_bar": 264,
      "size": 876.698,
      "equity_after": 1703.0722
    },
    {
      "pair": "TAC/USD",
      "entry": 0.00542,
      "exit": 0.004607,
      "pnl": -131.8263,
      "pnl_pct": -15.481,
      "reason": "FIXED STOP",
      "bars": 8,
      "entry_bar": 264,
      "exit_bar": 272,
      "size": 851.5361,
      "equity_after": 719.7098
    },
    {
      "pair": "MIRA/USD",
      "entry": 0.1698,
      "exit": 0.14433,
      "pnl": -109.529,
      "pnl_pct": -15.481,
      "reason": "FIXED STOP",
      "bars": 13,
      "entry_bar": 260,
      "exit_bar": 273,
      "size": 707.5062,
      "equity_after": 597.9772
    },
    {
      "pair": "MIR/USD",
      "entry": 0.00746,
      "exit": 0.00689,
      "pnl": -69.3226,
      "pnl_pct": -8.1409,
      "reason": "TIME MAX",
      "bars": 15,
      "entry_bar": 264,
      "exit_bar": 279,
      "size": 851.5361,
      "equity_after": 782.2135
    },
    {
      "pair": "ANKR/USD",
      "entry": 0.00778,
      "exit": 0.00792,
      "pnl": 9.1749,
      "pnl_pct": 1.2748,
      "reason": "RSI RECOVERY",
      "bars": 10,
      "entry_bar": 272,
      "exit_bar": 282,
      "size": 719.7098,
      "equity_after": 728.8847
    },
    {
      "pair": "QTUM/USD",
      "entry": 1.42812,
      "exit": 1.53066,
      "pnl": 51.9499,
      "pnl_pct": 6.6414,
      "reason": "DC TARGET",
      "bars": 4,
      "entry_bar": 279,
      "exit_bar": 283,
      "size": 782.2135,
      "equity_after": 834.1635
    },
    {
      "pair": "XAUT/USD",
      "entry": 4163.0,
      "exit": 4205.0,
      "pnl": 3.5443,
      "pnl_pct": 0.4863,
      "reason": "RSI RECOVERY",
      "bars": 2,
      "entry_bar": 282,
      "exit_bar": 284,
      "size": 728.8847,
      "equity_after": 732.429
    },
    {
      "pair": "TRU/USD",
      "entry": 0.01179,
      "exit": 0.01233,
      "pnl": 24.2076,
      "pnl_pct": 4.0482,
      "reason": "BB TARGET",
      "bars": 13,
      "entry_bar": 273,
      "exit_bar": 286,
      "size": 597.9772,
      "equity_after": 622.1848
    },
    {
      "pair": "QNT/USD",
      "entry": 95.56,
      "exit": 95.89,
      "pnl": -1.0923,
      "pnl_pct": -0.1756,
      "reason": "RSI RECOVERY",
      "bars": 2,
      "entry_bar": 286,
      "exit_bar": 288,
      "size": 622.1848,
      "equity_after": 621.0924
    },
    {
      "pair": "RIZE/USD",
      "entry": 0.012263,
      "exit": 0.012066,
      "pnl": -17.7033,
      "pnl_pct": -2.1223,
      "reason": "RSI RECOVERY",
      "bars": 6,
      "entry_bar": 283,
      "exit_bar": 289,
      "size": 834.1635,
      "equity_after": 816.4602
    },
    {
      "pair": "XAUT/USD",
      "entry": 4205.4,
      "exit": 4198.4,
      "pnl": -5.6011,
      "pnl_pct": -0.686,
      "reason": "RSI RECOVERY",
      "bars": 4,
      "entry_bar": 289,
      "exit_bar": 293,
      "size": 816.4602,
      "equity_after": 810.8591
    },
    {
      "pair": "BLUE/USD",
      "entry": 0.03637,
      "exit": 0.03737,
      "pnl": 16.2773,
      "pnl_pct": 2.2224,
      "reason": "BB TARGET",
      "bars": 10,
      "entry_bar": 284,
      "exit_bar": 294,
      "size": 732.429,
      "equity_after": 748.7063
    },
    {
      "pair": "JST/USD",
      "entry": 0.03919,
      "exit": 0.04066,
      "pnl": 20.0067,
      "pnl_pct": 3.2212,
      "reason": "RSI RECOVERY",
      "bars": 11,
      "entry_bar": 288,
      "exit_bar": 299,
      "size": 621.0924,
      "equity_after": 641.0991
    },
    {
      "pair": "AI3/USD",
      "entry": 0.0325,
      "exit": 0.0326,
      "pnl": -1.5956,
      "pnl_pct": -0.2131,
      "reason": "RSI RECOVERY",
      "bars": 5,
      "entry_bar": 294,
      "exit_bar": 299,
      "size": 748.7063,
      "equity_after": 1388.2098
    },
    {
      "pair": "AKE/USD",
      "entry": 0.0003678,
      "exit": 0.0003762,
      "pnl": 12.2018,
      "pnl_pct": 1.7579,
      "reason": "RSI RECOVERY",
      "bars": 5,
      "entry_bar": 299,
      "exit_bar": 304,
      "size": 694.1049,
      "equity_after": 706.3067
    },
    {
      "pair": "ACA/USD",
      "entry": 0.01024,
      "exit": 0.01128,
      "pnl": 67.875,
      "pnl_pct": 9.6098,
      "reason": "RSI RECOVERY",
      "bars": 3,
      "entry_bar": 304,
      "exit_bar": 307,
      "size": 706.3067,
      "equity_after": 774.1816
    },
    {
      "pair": "RIZE/USD",
      "entry": 0.01127,
      "exit": 0.010271,
      "pnl": -75.9061,
      "pnl_pct": -9.3612,
      "reason": "TIME MAX",
      "bars": 15,
      "entry_bar": 293,
      "exit_bar": 308,
      "size": 810.8591,
      "equity_after": 734.953
    },
    {
      "pair": "EAT/USD",
      "entry": 0.02929,
      "exit": 0.03087,
      "pnl": 33.7356,
      "pnl_pct": 4.8603,
      "reason": "BB TARGET",
      "bars": 10,
      "entry_bar": 299,
      "exit_bar": 309,
      "size": 694.1049,
      "equity_after": 727.8405
    },
    {
      "pair": "AURA/USD",
      "entry": 0.03657,
      "exit": 0.03807,
      "pnl": 27.6465,
      "pnl_pct": 3.5711,
      "reason": "RSI RECOVERY",
      "bars": 6,
      "entry_bar": 307,
      "exit_bar": 313,
      "size": 774.1816,
      "equity_after": 801.8281
    },
    {
      "pair": "VERSE/USD",
      "entry": 0.092,
      "exit": 0.092,
      "pnl": -3.8218,
      "pnl_pct": -0.52,
      "reason": "RSI RECOVERY",
      "bars": 9,
      "entry_bar": 308,
      "exit_bar": 317,
      "size": 734.953,
      "equity_after": 731.1312
    },
    {
      "pair": "ANIME/USD",
      "entry": 0.006462,
      "exit": 0.006816,
      "pnl": 35.984,
      "pnl_pct": 4.9439,
      "reason": "RSI RECOVERY",
      "bars": 8,
      "entry_bar": 309,
      "exit_bar": 317,
      "size": 727.8405,
      "equity_after": 1494.9558
    },
    {
      "pair": "TRUST/USD",
      "entry": 0.10909,
      "exit": 0.11347,
      "pnl": 27.9405,
      "pnl_pct": 3.4846,
      "reason": "RSI RECOVERY",
      "bars": 9,
      "entry_bar": 313,
      "exit_bar": 322,
      "size": 801.8281,
      "equity_after": 829.7686
    },
    {
      "pair": "CVC/USD",
      "entry": 0.0476,
      "exit": 0.0472,
      "pnl": -10.1519,
      "pnl_pct": -1.3582,
      "reason": "RSI RECOVERY",
      "bars": 6,
      "entry_bar": 317,
      "exit_bar": 323,
      "size": 747.4779,
      "equity_after": 737.326
    },
    {
      "pair": "GRASS/USD",
      "entry": 0.3004,
      "exit": 0.3402,
      "pnl": 105.3354,
      "pnl_pct": 12.6946,
      "reason": "RSI RECOVERY",
      "bars": 2,
      "entry_bar": 322,
      "exit_bar": 324,
      "size": 829.7686,
      "equity_after": 935.104
    },
    {
      "pair": "SYRUP/USD",
      "entry": 0.27237,
      "exit": 0.27574,
      "pnl": 6.6773,
      "pnl_pct": 0.7141,
      "reason": "BB TARGET",
      "bars": 1,
      "entry_bar": 324,
      "exit_bar": 325,
      "size": 935.104,
      "equity_after": 941.7813
    },
    {
      "pair": "NIGHT/USD",
      "entry": 0.0486,
      "exit": 0.04825,
      "pnl": -9.256,
      "pnl_pct": -1.2383,
      "reason": "RSI RECOVERY",
      "bars": 14,
      "entry_bar": 317,
      "exit_bar": 331,
      "size": 747.4779,
      "equity_after": 738.2219
    },
    {
      "pair": "STABLE/USD",
      "entry": 0.02402,
      "exit": 0.02556,
      "pnl": 43.3154,
      "pnl_pct": 5.8747,
      "reason": "RSI RECOVERY",
      "bars": 9,
      "entry_bar": 323,
      "exit_bar": 332,
      "size": 737.326,
      "equity_after": 780.6414
    },
    {
      "pair": "LIT/USD",
      "entry": 0.1395,
      "exit": 0.1384,
      "pnl": -12.3042,
      "pnl_pct": -1.3065,
      "reason": "BB TARGET",
      "bars": 13,
      "entry_bar": 325,
      "exit_bar": 338,
      "size": 941.7813,
      "equity_after": 929.4771
    },
    {
      "pair": "ACA/USD",
      "entry": 0.01193,
      "exit": 0.011,
      "pnl": -61.237,
      "pnl_pct": -8.2952,
      "reason": "TIME MAX",
      "bars": 15,
      "entry_bar": 331,
      "exit_bar": 346,
      "size": 738.2219,
      "equity_after": 676.9849
    },
    {
      "pair": "PUMP/USD",
      "entry": 0.00287,
      "exit": 0.002794,
      "pnl": -24.6776,
      "pnl_pct": -3.1612,
      "reason": "TIME MAX",
      "bars": 15,
      "entry_bar": 332,
      "exit_bar": 347,
      "size": 780.6414,
      "equity_after": 755.9637
    },
    {
      "pair": "ENJ/USD",
      "entry": 0.0319,
      "exit": 0.0315,
      "pnl": -16.4579,
      "pnl_pct": -1.7707,
      "reason": "RSI RECOVERY",
      "bars": 9,
      "entry_bar": 338,
      "exit_bar": 347,
      "size": 929.4771,
      "equity_after": 1668.983
    },
    {
      "pair": "SIDEKICK/USD",
      "entry": 0.00625,
      "exit": 0.00635,
      "pnl": 7.2833,
      "pnl_pct": 1.0758,
      "reason": "RSI RECOVERY",
      "bars": 11,
      "entry_bar": 346,
      "exit_bar": 357,
      "size": 676.9849,
      "equity_after": 684.2682
    },
    {
      "pair": "RUJI/USD",
      "entry": 0.3158,
      "exit": 0.317,
      "pnl": -1.1766,
      "pnl_pct": -0.141,
      "reason": "RSI RECOVERY",
      "bars": 11,
      "entry_bar": 347,
      "exit_bar": 358,
      "size": 834.4915,
      "equity_after": 833.3148
    },
    {
      "pair": "XMN/USD",
      "entry": 0.03679,
      "exit": 0.03737,
      "pnl": 7.2014,
      "pnl_pct": 1.0524,
      "reason": "RSI RECOVERY",
      "bars": 3,
      "entry_bar": 357,
      "exit_bar": 360,
      "size": 684.2682,
      "equity_after": 691.4695
    },
    {
      "pair": "CHEX/USD",
      "entry": 0.0359,
      "exit": 0.0329,
      "pnl": -73.8927,
      "pnl_pct": -8.8548,
      "reason": "TIME MAX",
      "bars": 15,
      "entry_bar": 347,
      "exit_bar": 362,
      "size": 834.4915,
      "equity_after": 760.5988
    },
    {
      "pair": "ZEC/USD",
      "entry": 402.7,
      "exit": 404.71,
      "pnl": -0.1847,
      "pnl_pct": -0.0222,
      "reason": "RSI RECOVERY",
      "bars": 10,
      "entry_bar": 358,
      "exit_bar": 368,
      "size": 833.3148,
      "equity_after": 833.1301
    },
    {
      "pair": "MNT/USD",
      "entry": 1.2486,
      "exit": 1.3143,
      "pnl": 39.3922,
      "pnl_pct": 4.7282,
      "reason": "DC TARGET",
      "bars": 1,
      "entry_bar": 368,
      "exit_bar": 369,
      "size": 833.1301,
      "equity_after": 872.5223
    },
    {
      "pair": "ACH/USD",
      "entry": 0.00867,
      "exit": 0.00784,
      "pnl": -69.6196,
      "pnl_pct": -10.0684,
      "reason": "TIME MAX",
      "bars": 15,
      "entry_bar": 360,
      "exit_bar": 375,
      "size": 691.4695,
      "equity_after": 621.8499
    },
    {
      "pair": "GUN/USD",
      "entry": 0.01529,
      "exit": 0.0129965,
      "pnl": -135.0752,
      "pnl_pct": -15.481,
      "reason": "FIXED STOP",
      "bars": 6,
      "entry_bar": 369,
      "exit_bar": 375,
      "size": 872.5223,
      "equity_after": 1359.2971
    },
    {
      "pair": "GNO/USD",
      "entry": 116.72,
      "exit": 113.51,
      "pnl": -24.8185,
      "pnl_pct": -3.263,
      "reason": "TIME MAX",
      "bars": 15,
      "entry_bar": 362,
      "exit_bar": 377,
      "size": 760.5988,
      "equity_after": 735.7803
    },
    {
      "pair": "RSC/USD",
      "entry": 0.138,
      "exit": 0.1387,
      "pnl": -0.0956,
      "pnl_pct": -0.0141,
      "reason": "RSI RECOVERY",
      "bars": 2,
      "entry_bar": 375,
      "exit_bar": 377,
      "size": 679.6485,
      "equity_after": 1415.3332
    },
    {
      "pair": "KTA/USD",
      "entry": 0.2352,
      "exit": 0.2614,
      "pnl": 71.9781,
      "pnl_pct": 10.5905,
      "reason": "RSI RECOVERY",
      "bars": 3,
      "entry_bar": 375,
      "exit_bar": 378,
      "size": 679.6485,
      "equity_after": 751.6267
    },
    {
      "pair": "MYX/USD",
      "entry": 3.176,
      "exit": 2.6996,
      "pnl": -109.5539,
      "pnl_pct": -15.481,
      "reason": "FIXED STOP",
      "bars": 4,
      "entry_bar": 377,
      "exit_bar": 381,
      "size": 707.6666,
      "equity_after": 598.1127
    },
    {
      "pair": "0G/USD",
      "entry": 0.713,
      "exit": 0.773,
      "pnl": 55.7165,
      "pnl_pct": 7.8733,
      "reason": "BB TARGET",
      "bars": 8,
      "entry_bar": 377,
      "exit_bar": 385,
      "size": 707.6666,
      "equity_after": 763.3831
    },
    {
      "pair": "GRASS/USD",
      "entry": 0.2849,
      "exit": 0.2973,
      "pnl": 28.7203,
      "pnl_pct": 3.8211,
      "reason": "RSI RECOVERY",
      "bars": 7,
      "entry_bar": 378,
      "exit_bar": 385,
      "size": 751.6267,
      "equity_after": 1543.73
    },
    {
      "pair": "SOMI/USD",
      "entry": 0.247,
      "exit": 0.2836,
      "pnl": 85.2866,
      "pnl_pct": 14.2593,
      "reason": "RSI RECOVERY",
      "bars": 6,
      "entry_bar": 381,
      "exit_bar": 387,
      "size": 598.1127,
      "equity_after": 683.3993
    },
    {
      "pair": "BRL1/USD",
      "entry": 0.18882,
      "exit": 0.19038,
      "pnl": 2.3467,
      "pnl_pct": 0.304,
      "reason": "RSI RECOVERY",
      "bars": 6,
      "entry_bar": 385,
      "exit_bar": 391,
      "size": 771.865,
      "equity_after": 774.2118
    },
    {
      "pair": "GUN/USD",
      "entry": 0.01229,
      "exit": 0.0121,
      "pnl": -15.9155,
      "pnl_pct": -2.062,
      "reason": "RSI RECOVERY",
      "bars": 8,
      "entry_bar": 385,
      "exit_bar": 393,
      "size": 771.865,
      "equity_after": 755.9495
    },
    {
      "pair": "ICNT/USD",
      "entry": 0.4381,
      "exit": 0.372385,
      "pnl": -117.0285,
      "pnl_pct": -15.481,
      "reason": "FIXED STOP",
      "bars": 3,
      "entry_bar": 393,
      "exit_bar": 396,
      "size": 755.9495,
      "equity_after": 638.921
    },
    {
      "pair": "SYND/USD",
      "entry": 0.0529,
      "exit": 0.0582,
      "pnl": 73.34,
      "pnl_pct": 9.4729,
      "reason": "RSI RECOVERY",
      "bars": 6,
      "entry_bar": 391,
      "exit_bar": 397,
      "size": 774.2118,
      "equity_after": 847.5517
    },
    {
      "pair": "BSU/USD",
      "entry": 0.12489,
      "exit": 0.13169,
      "pnl": 33.5592,
      "pnl_pct": 4.9106,
      "reason": "RSI RECOVERY",
      "bars": 12,
      "entry_bar": 387,
      "exit_bar": 399,
      "size": 683.3993,
      "equity_after": 716.9586
    },
    {
      "pair": "SGB/USD",
      "entry": 0.00209,
      "exit": 0.0022,
      "pnl": 40.0847,
      "pnl_pct": 4.7295,
      "reason": "RSI RECOVERY",
      "bars": 3,
      "entry_bar": 397,
      "exit_bar": 400,
      "size": 847.5517,
      "equity_after": 887.6365
    },
    {
      "pair": "LMWR/USD",
      "entry": 0.0322,
      "exit": 0.033,
      "pnl": 17.38,
      "pnl_pct": 1.958,
      "reason": "RSI RECOVERY",
      "bars": 2,
      "entry_bar": 400,
      "exit_bar": 402,
      "size": 887.6365,
      "equity_after": 905.0165
    },
    {
      "pair": "LRC/USD",
      "entry": 0.0562,
      "exit": 0.0559,
      "pnl": -9.5246,
      "pnl_pct": -1.0524,
      "reason": "RSI RECOVERY",
      "bars": 8,
      "entry_bar": 402,
      "exit_bar": 410,
      "size": 905.0165,
      "equity_after": 895.4919
    },
    {
      "pair": "CC/USD",
      "entry": 0.13143,
      "exit": 0.12251,
      "pnl": -46.5725,
      "pnl_pct": -7.2892,
      "reason": "TIME MAX",
      "bars": 15,
      "entry_bar": 396,
      "exit_bar": 411,
      "size": 638.921,
      "equity_after": 592.3485
    },
    {
      "pair": "ANIME/USD",
      "entry": 0.008401,
      "exit": 0.00757,
      "pnl": -74.463,
      "pnl_pct": -10.386,
      "reason": "TIME MAX",
      "bars": 15,
      "entry_bar": 399,
      "exit_bar": 414,
      "size": 716.9586,
      "equity_after": 642.4955
    },
    {
      "pair": "ALCH/USD",
      "entry": 0.1637,
      "exit": 0.139145,
      "pnl": -91.7015,
      "pnl_pct": -15.481,
      "reason": "FIXED STOP",
      "bars": 5,
      "entry_bar": 411,
      "exit_bar": 416,
      "size": 592.3485,
      "equity_after": 500.647
    },
    {
      "pair": "BCH/USD",
      "entry": 572.0,
      "exit": 585.61,
      "pnl": 16.5951,
      "pnl_pct": 1.8532,
      "reason": "RSI RECOVERY",
      "bars": 9,
      "entry_bar": 410,
      "exit_bar": 419,
      "size": 895.4919,
      "equity_after": 912.087
    },
    {
      "pair": "BLUAI/USD",
      "entry": 0.004335,
      "exit": 0.004573,
      "pnl": 24.8117,
      "pnl_pct": 4.9559,
      "reason": "RSI RECOVERY",
      "bars": 6,
      "entry_bar": 416,
      "exit_bar": 422,
      "size": 500.647,
      "equity_after": 525.4587
    },
    {
      "pair": "EWT/USD",
      "entry": 0.675,
      "exit": 0.725,
      "pnl": 44.1275,
      "pnl_pct": 6.8681,
      "reason": "RSI RECOVERY",
      "bars": 13,
      "entry_bar": 414,
      "exit_bar": 427,
      "size": 642.4955,
      "equity_after": 686.6231
    },
    {
      "pair": "SWEAT/USD",
      "entry": 0.001399,
      "exit": 0.001407,
      "pnl": 0.2646,
      "pnl_pct": 0.0504,
      "reason": "BB TARGET",
      "bars": 11,
      "entry_bar": 422,
      "exit_bar": 433,
      "size": 525.4587,
      "equity_after": 525.7233
    },
    {
      "pair": "BOB/USD",
      "entry": 0.009,
      "exit": 0.00828,
      "pnl": -77.5201,
      "pnl_pct": -8.4992,
      "reason": "TIME MAX",
      "bars": 15,
      "entry_bar": 419,
      "exit_bar": 434,
      "size": 912.087,
      "equity_after": 834.5669
    },
    {
      "pair": "ES/USD",
      "entry": 0.0839,
      "exit": 0.0864,
      "pnl": 16.8359,
      "pnl_pct": 2.452,
      "reason": "RSI RECOVERY",
      "bars": 9,
      "entry_bar": 427,
      "exit_bar": 436,
      "size": 686.6231,
      "equity_after": 703.459
    },
    {
      "pair": "NOBODY/USD",
      "entry": 0.0189,
      "exit": 0.0193,
      "pnl": 8.3637,
      "pnl_pct": 1.5909,
      "reason": "RSI RECOVERY",
      "bars": 3,
      "entry_bar": 433,
      "exit_bar": 436,
      "size": 525.7233,
      "equity_after": 1237.546
    },
    {
      "pair": "PUPS/USD",
      "entry": 0.00304,
      "exit": 0.00311,
      "pnl": 10.9934,
      "pnl_pct": 1.7766,
      "reason": "RSI RECOVERY",
      "bars": 3,
      "entry_bar": 436,
      "exit_bar": 439,
      "size": 618.773,
      "equity_after": 629.7664
    },
    {
      "pair": "PLANCK/USD",
      "entry": 0.00689,
      "exit": 0.0058565,
      "pnl": -97.4941,
      "pnl_pct": -15.481,
      "reason": "FIXED STOP",
      "bars": 3,
      "entry_bar": 439,
      "exit_bar": 442,
      "size": 629.7664,
      "equity_after": 532.2723
    },
    {
      "pair": "ADX/USD",
      "entry": 0.10376,
      "exit": 0.10949,
      "pnl": 26.5497,
      "pnl_pct": 4.988,
      "reason": "DC TARGET",
      "bars": 1,
      "entry_bar": 442,
      "exit_bar": 443,
      "size": 532.2723,
      "equity_after": 558.822
    },
    {
      "pair": "MERL/USD",
      "entry": 0.37268,
      "exit": 0.316778,
      "pnl": -129.1993,
      "pnl_pct": -15.481,
      "reason": "FIXED STOP",
      "bars": 11,
      "entry_bar": 434,
      "exit_bar": 445,
      "size": 834.5669,
      "equity_after": 705.3676
    },
    {
      "pair": "BANANAS31/USD",
      "entry": 0.003492,
      "exit": 0.003533,
      "pnl": 3.6383,
      "pnl_pct": 0.6511,
      "reason": "RSI RECOVERY",
      "bars": 4,
      "entry_bar": 443,
      "exit_bar": 447,
      "size": 558.822,
      "equity_after": 562.4603
    },
    {
      "pair": "CAMP/USD",
      "entry": 0.00696,
      "exit": 0.00708,
      "pnl": 8.462,
      "pnl_pct": 1.1997,
      "reason": "RSI RECOVERY",
      "bars": 5,
      "entry_bar": 445,
      "exit_bar": 450,
      "size": 705.3676,
      "equity_after": 713.8296
    },
    {
      "pair": "PRCL/USD",
      "entry": 0.0209,
      "exit": 0.0191,
      "pnl": -56.3705,
      "pnl_pct": -9.11,
      "reason": "TIME MAX",
      "bars": 15,
      "entry_bar": 436,
      "exit_bar": 451,
      "size": 618.773,
      "equity_after": 562.4025
    },
    {
      "pair": "FORTH/USD",
      "entry": 1.547,
      "exit": 1.569,
      "pnl": 5.0532,
      "pnl_pct": 0.8984,
      "reason": "RSI RECOVERY",
      "bars": 6,
      "entry_bar": 447,
      "exit_bar": 453,
      "size": 562.4603,
      "equity_after": 567.5135
    },
    {
      "pair": "PEAQ/USD",
      "entry": 0.03136,
      "exit": 0.03272,
      "pnl": 21.402,
      "pnl_pct": 3.8055,
      "reason": "RSI RECOVERY",
      "bars": 2,
      "entry_bar": 451,
      "exit_bar": 453,
      "size": 562.4025,
      "equity_after": 1151.318
    },
    {
      "pair": "AUDIO/USD",
      "entry": 0.0286,
      "exit": 0.0293,
      "pnl": 13.714,
      "pnl_pct": 1.9212,
      "reason": "RSI RECOVERY",
      "bars": 8,
      "entry_bar": 450,
      "exit_bar": 458,
      "size": 713.8296,
      "equity_after": 727.5436
    },
    {
      "pair": "RLC/USD",
      "entry": 0.6349,
      "exit": 0.6361,
      "pnl": -1.9082,
      "pnl_pct": -0.3315,
      "reason": "RSI RECOVERY",
      "bars": 8,
      "entry_bar": 453,
      "exit_bar": 461,
      "size": 575.659,
      "equity_after": 573.7508
    },
    {
      "pair": "DRIFT/USD",
      "entry": 0.1536,
      "exit": 0.1597,
      "pnl": 19.8086,
      "pnl_pct": 3.441,
      "reason": "RSI RECOVERY",
      "bars": 10,
      "entry_bar": 453,
      "exit_bar": 463,
      "size": 575.659,
      "equity_after": 595.4676
    },
    {
      "pair": "CHECK/USD",
      "entry": 0.055556,
      "exit": 0.065123,
      "pnl": 95.5621,
      "pnl_pct": 16.6557,
      "reason": "RSI RECOVERY",
      "bars": 3,
      "entry_bar": 461,
      "exit_bar": 464,
      "size": 573.7508,
      "equity_after": 669.3129
    },
    {
      "pair": "KERNEL/USD",
      "entry": 0.06993,
      "exit": 0.07168,
      "pnl": 11.7664,
      "pnl_pct": 1.976,
      "reason": "RSI RECOVERY",
      "bars": 6,
      "entry_bar": 463,
      "exit_bar": 469,
      "size": 595.4676,
      "equity_after": 607.234
    },
    {
      "pair": "AVNT/USD",
      "entry": 0.34674,
      "exit": 0.36071,
      "pnl": 25.453,
      "pnl_pct": 3.4985,
      "reason": "RSI RECOVERY",
      "bars": 12,
      "entry_bar": 458,
      "exit_bar": 470,
      "size": 727.5436,
      "equity_after": 752.9966
    },
    {
      "pair": "ZRX/USD",
      "entry": 0.139,
      "exit": 0.147,
      "pnl": 34.941,
      "pnl_pct": 5.2204,
      "reason": "RSI RECOVERY",
      "bars": 7,
      "entry_bar": 464,
      "exit_bar": 471,
      "size": 669.3129,
      "equity_after": 704.2539
    },
    {
      "pair": "NYM/USD",
      "entry": 0.0373,
      "exit": 0.0388,
      "pnl": 26.2871,
      "pnl_pct": 3.491,
      "reason": "RSI RECOVERY",
      "bars": 2,
      "entry_bar": 470,
      "exit_bar": 472,
      "size": 752.9966,
      "equity_after": 779.2836
    },
    {
      "pair": "H/USD",
      "entry": 0.16784,
      "exit": 0.1702,
      "pnl": 5.3585,
      "pnl_pct": 0.8824,
      "reason": "RSI RECOVERY",
      "bars": 5,
      "entry_bar": 469,
      "exit_bar": 474,
      "size": 607.234,
      "equity_after": 612.5925
    },
    {
      "pair": "ACA/USD",
      "entry": 0.00886,
      "exit": 0.0094,
      "pnl": 39.1492,
      "pnl_pct": 5.559,
      "reason": "RSI RECOVERY",
      "bars": 3,
      "entry_bar": 471,
      "exit_bar": 474,
      "size": 704.2539,
      "equity_after": 1355.9956
    },
    {
      "pair": "CYBER/USD",
      "entry": 0.765,
      "exit": 0.768,
      "pnl": -1.0042,
      "pnl_pct": -0.1289,
      "reason": "RSI RECOVERY",
      "bars": 2,
      "entry_bar": 472,
      "exit_bar": 474,
      "size": 779.2836,
      "equity_after": 2134.2751
    },
    {
      "pair": "GOMINING/USD",
      "entry": 0.4325,
      "exit": 0.4564,
      "pnl": 35.5118,
      "pnl_pct": 4.9916,
      "reason": "RSI RECOVERY",
      "bars": 5,
      "entry_bar": 474,
      "exit_bar": 479,
      "size": 711.425,
      "equity_after": 746.9368
    },
    {
      "pair": "UXLINK/USD",
      "entry": 0.01055,
      "exit": 0.01279,
      "pnl": 146.9592,
      "pnl_pct": 20.657,
      "reason": "DC TARGET",
      "bars": 5,
      "entry_bar": 474,
      "exit_bar": 479,
      "size": 711.425,
      "equity_after": 1605.3211
    },
    {
      "pair": "KIN/USD",
      "entry": 5.96e-07,
      "exit": 7.1e-07,
      "pnl": 148.956,
      "pnl_pct": 18.5578,
      "reason": "DC TARGET",
      "bars": 1,
      "entry_bar": 479,
      "exit_bar": 480,
      "size": 802.6605,
      "equity_after": 951.6166
    },
    {
      "pair": "SHX/USD",
      "entry": 0.00987,
      "exit": 0.009899,
      "pnl": -1.6145,
      "pnl_pct": -0.2269,
      "reason": "RSI RECOVERY",
      "bars": 12,
      "entry_bar": 474,
      "exit_bar": 486,
      "size": 711.425,
      "equity_after": 709.8105
    },
    {
      "pair": "ALLO/USD",
      "entry": 0.0759,
      "exit": 0.064515,
      "pnl": -124.2599,
      "pnl_pct": -15.481,
      "reason": "FIXED STOP",
      "bars": 8,
      "entry_bar": 479,
      "exit_bar": 487,
      "size": 802.6605,
      "equity_after": 678.4007
    },
    {
      "pair": "KET/USD",
      "entry": 0.008,
      "exit": 0.0096,
      "pnl": 137.902,
      "pnl_pct": 19.428,
      "reason": "BB TARGET",
      "bars": 1,
      "entry_bar": 486,
      "exit_bar": 487,
      "size": 709.8105,
      "equity_after": 1526.1131
    },
    {
      "pair": "REN/USD",
      "entry": 0.00656,
      "exit": 0.00609,
      "pnl": -72.951,
      "pnl_pct": -7.666,
      "reason": "TIME MAX",
      "bars": 15,
      "entry_bar": 480,
      "exit_bar": 495,
      "size": 951.6166,
      "equity_after": 878.6656
    },
    {
      "pair": "ICNT/USD",
      "entry": 0.3752,
      "exit": 0.3943,
      "pnl": 34.7754,
      "pnl_pct": 4.5574,
      "reason": "RSI RECOVERY",
      "bars": 11,
      "entry_bar": 487,
      "exit_bar": 498,
      "size": 763.0566,
      "equity_after": 797.832
    },
    {
      "pair": "GRIFFAIN/USD",
      "entry": 0.02145,
      "exit": 0.02167,
      "pnl": 4.4195,
      "pnl_pct": 0.503,
      "reason": "RSI RECOVERY",
      "bars": 6,
      "entry_bar": 495,
      "exit_bar": 501,
      "size": 878.6656,
      "equity_after": 883.085
    },
    {
      "pair": "CHZ/USD",
      "entry": 0.04265,
      "exit": 0.04443,
      "pnl": 29.0623,
      "pnl_pct": 3.6427,
      "reason": "BB TARGET",
      "bars": 3,
      "entry_bar": 498,
      "exit_bar": 501,
      "size": 797.832,
      "equity_after": 1709.9793
    },
    {
      "pair": "PIPE/USD",
      "entry": 0.06164,
      "exit": 0.06128,
      "pnl": -8.4128,
      "pnl_pct": -1.1025,
      "reason": "TIME MAX",
      "bars": 15,
      "entry_bar": 487,
      "exit_bar": 502,
      "size": 763.0566,
      "equity_after": 754.6437
    },
    {
      "pair": "BNB/USD",
      "entry": 884.26,
      "exit": 894.82,
      "pnl": 5.0645,
      "pnl_pct": 0.6711,
      "reason": "RSI RECOVERY",
      "bars": 5,
      "entry_bar": 502,
      "exit_bar": 507,
      "size": 754.6437,
      "equity_after": 759.7083
    },
    {
      "pair": "PARTI/USD",
      "entry": 0.0954,
      "exit": 0.0898,
      "pnl": -54.5035,
      "pnl_pct": -6.3748,
      "reason": "TIME MAX",
      "bars": 15,
      "entry_bar": 501,
      "exit_bar": 516,
      "size": 854.9896,
      "equity_after": 800.4861
    },
    {
      "pair": "XPL/USD",
      "entry": 0.1735,
      "exit": 0.166,
      "pnl": -41.3091,
      "pnl_pct": -4.8315,
      "reason": "TIME MAX",
      "bars": 15,
      "entry_bar": 501,
      "exit_bar": 516,
      "size": 854.9896,
      "equity_after": 1614.1667
    },
    {
      "pair": "EDU/USD",
      "entry": 0.12508,
      "exit": 0.13908,
      "pnl": 80.8613,
      "pnl_pct": 10.6437,
      "reason": "RSI RECOVERY",
      "bars": 9,
      "entry_bar": 507,
      "exit_bar": 516,
      "size": 759.7083,
      "equity_after": 2454.7363
    },
    {
      "pair": "LSK/USD",
      "entry": 0.204443,
      "exit": 0.205167,
      "pnl": -1.3647,
      "pnl_pct": -0.1668,
      "reason": "RSI RECOVERY",
      "bars": 2,
      "entry_bar": 516,
      "exit_bar": 518,
      "size": 818.2454,
      "equity_after": 816.8807
    },
    {
      "pair": "STRK/USD",
      "entry": 0.08267,
      "exit": 0.08158,
      "pnl": -15.0154,
      "pnl_pct": -1.8351,
      "reason": "RSI RECOVERY",
      "bars": 7,
      "entry_bar": 516,
      "exit_bar": 523,
      "size": 818.2454,
      "equity_after": 803.2301
    },
    {
      "pair": "CC/USD",
      "entry": 0.16564,
      "exit": 0.17378,
      "pnl": 35.1935,
      "pnl_pct": 4.3815,
      "reason": "RSI RECOVERY",
      "bars": 7,
      "entry_bar": 523,
      "exit_bar": 530,
      "size": 803.2301,
      "equity_after": 838.4236
    },
    {
      "pair": "ENSO/USD",
      "entry": 0.685,
      "exit": 0.666,
      "pnl": -26.8917,
      "pnl_pct": -3.2865,
      "reason": "TIME MAX",
      "bars": 15,
      "entry_bar": 516,
      "exit_bar": 531,
      "size": 818.2454,
      "equity_after": 791.3537
    },
    {
      "pair": "BABY/USD",
      "entry": 0.018,
      "exit": 0.01782,
      "pnl": -12.3953,
      "pnl_pct": -1.5174,
      "reason": "TIME MAX",
      "bars": 15,
      "entry_bar": 518,
      "exit_bar": 533,
      "size": 816.8807,
      "equity_after": 804.4853
    },
    {
      "pair": "XTZ/USD",
      "entry": 0.5548,
      "exit": 0.5745,
      "pnl": 25.3338,
      "pnl_pct": 3.0216,
      "reason": "RSI RECOVERY",
      "bars": 3,
      "entry_bar": 530,
      "exit_bar": 533,
      "size": 838.4236,
      "equity_after": 1668.2427
    },
    {
      "pair": "GMT/USD",
      "entry": 0.01897,
      "exit": 0.01967,
      "pnl": 26.3619,
      "pnl_pct": 3.1604,
      "reason": "RSI RECOVERY",
      "bars": 3,
      "entry_bar": 533,
      "exit_bar": 536,
      "size": 834.1213,
      "equity_after": 860.4833
    },
    {
      "pair": "APR/USD",
      "entry": 0.11827,
      "exit": 0.1005295,
      "pnl": -129.1303,
      "pnl_pct": -15.481,
      "reason": "FIXED STOP",
      "bars": 4,
      "entry_bar": 533,
      "exit_bar": 537,
      "size": 834.1213,
      "equity_after": 704.991
    },
    {
      "pair": "POL/USD",
      "entry": 0.1523,
      "exit": 0.1642,
      "pnl": 57.5568,
      "pnl_pct": 7.2732,
      "reason": "RSI RECOVERY",
      "bars": 7,
      "entry_bar": 531,
      "exit_bar": 538,
      "size": 791.3537,
      "equity_after": 848.9105
    },
    {
      "pair": "BLUAI/USD",
      "entry": 0.005559,
      "exit": 0.00668,
      "pnl": 168.5951,
      "pnl_pct": 19.5931,
      "reason": "RSI RECOVERY",
      "bars": 3,
      "entry_bar": 536,
      "exit_bar": 539,
      "size": 860.4833,
      "equity_after": 1029.0783
    },
    {
      "pair": "CQT/USD",
      "entry": 0.00087,
      "exit": 0.0009,
      "pnl": 20.5809,
      "pnl_pct": 2.9193,
      "reason": "RSI RECOVERY",
      "bars": 2,
      "entry_bar": 537,
      "exit_bar": 539,
      "size": 704.991,
      "equity_after": 1754.6502
    },
    {
      "pair": "CHILLHOUSE/USD",
      "entry": 0.00629,
      "exit": 0.00658,
      "pnl": 35.7818,
      "pnl_pct": 4.0785,
      "reason": "RSI RECOVERY",
      "bars": 2,
      "entry_bar": 539,
      "exit_bar": 541,
      "size": 877.3251,
      "equity_after": 913.1069
    },
    {
      "pair": "AIN/USD",
      "entry": 0.03861,
      "exit": 0.04038,
      "pnl": 34.4011,
      "pnl_pct": 4.0524,
      "reason": "RSI RECOVERY",
      "bars": 7,
      "entry_bar": 538,
      "exit_bar": 545,
      "size": 848.9105,
      "equity_after": 883.3116
    },
    {
      "pair": "CHILLHOUSE/USD",
      "entry": 0.00588,
      "exit": 0.00601,
      "pnl": 14.885,
      "pnl_pct": 1.6851,
      "reason": "RSI RECOVERY",
      "bars": 2,
      "entry_bar": 545,
      "exit_bar": 547,
      "size": 883.3116,
      "equity_after": 898.1967
    },
    {
      "pair": "MNGO/USD",
      "entry": 0.01923,
      "exit": 0.02137,
      "pnl": 92.8167,
      "pnl_pct": 10.5795,
      "reason": "RSI RECOVERY",
      "bars": 10,
      "entry_bar": 539,
      "exit_bar": 549,
      "size": 877.3251,
      "equity_after": 970.1418
    },
    {
      "pair": "PROVE/USD",
      "entry": 0.436,
      "exit": 0.4104,
      "pnl": -58.2224,
      "pnl_pct": -6.3763,
      "reason": "TIME MAX",
      "bars": 15,
      "entry_bar": 541,
      "exit_bar": 556,
      "size": 913.1069,
      "equity_after": 854.8845
    },
    {
      "pair": "REZ/USD",
      "entry": 0.00534,
      "exit": 0.0054,
      "pnl": 5.3952,
      "pnl_pct": 0.6007,
      "reason": "RSI RECOVERY",
      "bars": 10,
      "entry_bar": 547,
      "exit_bar": 557,
      "size": 898.1967,
      "equity_after": 903.5919
    },
    {
      "pair": "VVV/USD",
      "entry": 2.929,
      "exit": 3.03,
      "pnl": 26.3787,
      "pnl_pct": 2.9193,
      "reason": "RSI RECOVERY",
      "bars": 5,
      "entry_bar": 557,
      "exit_bar": 562,
      "size": 903.5919,
      "equity_after": 929.9705
    },
    {
      "pair": "SYRUP/USD",
      "entry": 0.3663,
      "exit": 0.36,
      "pnl": -21.6868,
      "pnl_pct": -2.2354,
      "reason": "TIME MAX",
      "bars": 15,
      "entry_bar": 549,
      "exit_bar": 564,
      "size": 970.1418,
      "equity_after": 948.455
    },
    {
      "pair": "B2/USD",
      "entry": 0.7237,
      "exit": 0.7404,
      "pnl": 16.5682,
      "pnl_pct": 1.7816,
      "reason": "RSI RECOVERY",
      "bars": 2,
      "entry_bar": 562,
      "exit_bar": 564,
      "size": 929.9705,
      "equity_after": 1894.9937
    },
    {
      "pair": "H/USD",
      "entry": 0.18397,
      "exit": 0.19721,
      "pnl": 63.0854,
      "pnl_pct": 6.6581,
      "reason": "RSI RECOVERY",
      "bars": 3,
      "entry_bar": 564,
      "exit_bar": 567,
      "size": 947.4969,
      "equity_after": 1010.5823
    },
    {
      "pair": "XMR/USD",
      "entry": 623.56,
      "exit": 638.84,
      "pnl": 16.4486,
      "pnl_pct": 1.9241,
      "reason": "RSI RECOVERY",
      "bars": 12,
      "entry_bar": 556,
      "exit_bar": 568,
      "size": 854.8845,
      "equity_after": 871.3331
    },
    {
      "pair": "CHEX/USD",
      "entry": 0.0652,
      "exit": 0.05542,
      "pnl": -146.682,
      "pnl_pct": -15.481,
      "reason": "FIXED STOP",
      "bars": 14,
      "entry_bar": 564,
      "exit_bar": 578,
      "size": 947.4969,
      "equity_after": 800.8149
    },
    {
      "pair": "INIT/USD",
      "entry": 0.0878,
      "exit": 0.0811,
      "pnl": -82.1719,
      "pnl_pct": -8.1311,
      "reason": "TIME MAX",
      "bars": 15,
      "entry_bar": 567,
      "exit_bar": 582,
      "size": 1010.5823,
      "equity_after": 928.4104
    },
    {
      "pair": "CELO/USD",
      "entry": 0.1226,
      "exit": 0.1191,
      "pnl": -29.3412,
      "pnl_pct": -3.3674,
      "reason": "TIME MAX",
      "bars": 15,
      "entry_bar": 568,
      "exit_bar": 583,
      "size": 871.3331,
      "equity_after": 841.9919
    },
    {
      "pair": "MXC/USD",
      "entry": 0.000881,
      "exit": 0.000983,
      "pnl": 102.3819,
      "pnl_pct": 11.0277,
      "reason": "RSI RECOVERY",
      "bars": 3,
      "entry_bar": 582,
      "exit_bar": 585,
      "size": 928.4104,
      "equity_after": 1030.7923
    },
    {
      "pair": "TRX/USD",
      "entry": 0.296446,
      "exit": 0.303876,
      "pnl": 15.8549,
      "pnl_pct": 1.9798,
      "reason": "RSI RECOVERY",
      "bars": 11,
      "entry_bar": 578,
      "exit_bar": 589,
      "size": 800.8149,
      "equity_after": 816.6698
    },
    {
      "pair": "CHZ/USD",
      "entry": 0.05182,
      "exit": 0.05114,
      "pnl": -15.3985,
      "pnl_pct": -1.8288,
      "reason": "RSI RECOVERY",
      "bars": 9,
      "entry_bar": 583,
      "exit_bar": 592,
      "size": 841.9919,
      "equity_after": 826.5934
    },
    {
      "pair": "FHE/USD",
      "entry": 0.1283,
      "exit": 0.14953,
      "pnl": 130.5376,
      "pnl_pct": 15.9841,
      "reason": "RSI RECOVERY",
      "bars": 7,
      "entry_bar": 589,
      "exit_bar": 596,
      "size": 816.6698,
      "equity_after": 947.2073
    },
    {
      "pair": "BERA/USD",
      "entry": 0.8488,
      "exit": 0.7301,
      "pnl": -149.1359,
      "pnl_pct": -14.4681,
      "reason": "TIME MAX",
      "bars": 15,
      "entry_bar": 585,
      "exit_bar": 600,
      "size": 1030.7923,
      "equity_after": 881.6564
    },
    {
      "pair": "PHA/USD",
      "entry": 0.03885,
      "exit": 0.04076,
      "pnl": 41.5214,
      "pnl_pct": 4.3836,
      "reason": "RSI RECOVERY",
      "bars": 7,
      "entry_bar": 596,
      "exit_bar": 603,
      "size": 947.2073,
      "equity_after": 988.7288
    },
    {
      "pair": "SCRT/USD",
      "entry": 0.1638,
      "exit": 0.169,
      "pnl": 23.3317,
      "pnl_pct": 2.6463,
      "reason": "RSI RECOVERY",
      "bars": 4,
      "entry_bar": 600,
      "exit_bar": 604,
      "size": 881.6564,
      "equity_after": 904.9881
    },
    {
      "pair": "GAIA/USD",
      "entry": 0.025475,
      "exit": 0.025345,
      "pnl": -8.5055,
      "pnl_pct": -1.029,
      "reason": "TIME MAX",
      "bars": 15,
      "entry_bar": 592,
      "exit_bar": 607,
      "size": 826.5934,
      "equity_after": 818.0879
    },
    {
      "pair": "COTI/USD",
      "entry": 0.01836,
      "exit": 0.01789,
      "pnl": -30.3862,
      "pnl_pct": -3.0733,
      "reason": "DC TARGET",
      "bars": 12,
      "entry_bar": 603,
      "exit_bar": 615,
      "size": 988.7288,
      "equity_after": 958.3426
    },
    {
      "pair": "STG/USD",
      "entry": 0.1665,
      "exit": 0.1764,
      "pnl": 44.2625,
      "pnl_pct": 5.4105,
      "reason": "RSI RECOVERY",
      "bars": 8,
      "entry_bar": 607,
      "exit_bar": 615,
      "size": 818.0879,
      "equity_after": 1820.693
    },
    {
      "pair": "BERA/USD",
      "entry": 0.6791,
      "exit": 0.6453,
      "pnl": -49.6317,
      "pnl_pct": -5.4842,
      "reason": "TIME MAX",
      "bars": 15,
      "entry_bar": 604,
      "exit_bar": 619,
      "size": 904.9881,
      "equity_after": 855.3564
    },
    {
      "pair": "CYBER/USD",
      "entry": 0.761,
      "exit": 0.793,
      "pnl": 31.4263,
      "pnl_pct": 3.6741,
      "reason": "BB TARGET",
      "bars": 1,
      "entry_bar": 619,
      "exit_bar": 620,
      "size": 855.3564,
      "equity_after": 886.7827
    },
    {
      "pair": "GUN/USD",
      "entry": 0.02894,
      "exit": 0.03077,
      "pnl": 52.6816,
      "pnl_pct": 5.787,
      "reason": "BB TARGET",
      "bars": 6,
      "entry_bar": 615,
      "exit_bar": 621,
      "size": 910.3465,
      "equity_after": 963.0282
    },
    {
      "pair": "MYX/USD",
      "entry": 5.666,
      "exit": 6.112,
      "pnl": 66.7379,
      "pnl_pct": 7.331,
      "reason": "RSI RECOVERY",
      "bars": 6,
      "entry_bar": 615,
      "exit_bar": 621,
      "size": 910.3465,
      "equity_after": 1940.1126
    },
    {
      "pair": "MF/USD",
      "entry": 0.00581,
      "exit": 0.00609,
      "pnl": 38.0141,
      "pnl_pct": 4.2867,
      "reason": "RSI RECOVERY",
      "bars": 4,
      "entry_bar": 620,
      "exit_bar": 624,
      "size": 886.7827,
      "equity_after": 924.7968
    },
    {
      "pair": "0G/USD",
      "entry": 0.828,
      "exit": 0.825,
      "pnl": -8.5499,
      "pnl_pct": -0.8814,
      "reason": "RSI RECOVERY",
      "bars": 13,
      "entry_bar": 621,
      "exit_bar": 634,
      "size": 970.0563,
      "equity_after": 961.5065
    },
    {
      "pair": "KOBAN/USD",
      "entry": 0.0001441,
      "exit": 0.000122485,
      "pnl": -74.4254,
      "pnl_pct": -15.481,
      "reason": "FIXED STOP",
      "bars": 3,
      "entry_bar": 634,
      "exit_bar": 637,
      "size": 480.7532,
      "equity_after": 406.3278
    },
    {
      "pair": "SUPER/USD",
      "entry": 0.1875,
      "exit": 0.1645,
      "pnl": -117.9557,
      "pnl_pct": -12.7548,
      "reason": "TIME MAX",
      "bars": 15,
      "entry_bar": 624,
      "exit_bar": 639,
      "size": 924.7968,
      "equity_after": 806.8411
    },
    {
      "pair": "BANANAS31/USD",
      "entry": 0.003991,
      "exit": 0.00339235,
      "pnl": -74.4254,
      "pnl_pct": -15.481,
      "reason": "FIXED STOP",
      "bars": 9,
      "entry_bar": 634,
      "exit_bar": 643,
      "size": 480.7532,
      "equity_after": 406.3278
    },
    {
      "pair": "ES/USD",
      "entry": 0.1382,
      "exit": 0.11747,
      "pnl": -124.9071,
      "pnl_pct": -15.481,
      "reason": "FIXED STOP",
      "bars": 4,
      "entry_bar": 639,
      "exit_bar": 643,
      "size": 806.8411,
      "equity_after": 1088.2618
    },
    {
      "pair": "BABY/USD",
      "entry": 0.01603,
      "exit": 0.01727,
      "pnl": 39.1523,
      "pnl_pct": 7.1954,
      "reason": "DC TARGET",
      "bars": 3,
      "entry_bar": 643,
      "exit_bar": 646,
      "size": 544.1309,
      "equity_after": 583.2832
    },
    {
      "pair": "TOKEN/USD",
      "entry": 0.003222,
      "exit": 0.004329,
      "pnl": 137.1284,
      "pnl_pct": 33.7482,
      "reason": "RSI RECOVERY",
      "bars": 10,
      "entry_bar": 637,
      "exit_bar": 647,
      "size": 406.3278,
      "equity_after": 543.4562
    },
    {
      "pair": "XNAP/USD",
      "entry": 0.00014,
      "exit": 0.000181,
      "pnl": 155.9153,
      "pnl_pct": 28.6896,
      "reason": "BB TARGET",
      "bars": 3,
      "entry_bar": 647,
      "exit_bar": 650,
      "size": 543.4562,
      "equity_after": 699.3714
    },
    {
      "pair": "SUPER/USD",
      "entry": 0.1429,
      "exit": 0.1507,
      "pnl": 26.7939,
      "pnl_pct": 4.9242,
      "reason": "RSI RECOVERY",
      "bars": 13,
      "entry_bar": 643,
      "exit_bar": 656,
      "size": 544.1309,
      "equity_after": 570.9249
    },
    {
      "pair": "ASTR/USD",
      "entry": 0.00824,
      "exit": 0.00874,
      "pnl": 31.5846,
      "pnl_pct": 5.5322,
      "reason": "RSI RECOVERY",
      "bars": 2,
      "entry_bar": 656,
      "exit_bar": 658,
      "size": 570.9249,
      "equity_after": 602.5095
    },
    {
      "pair": "REPV2/USD",
      "entry": 0.721,
      "exit": 0.683,
      "pnl": -33.6948,
      "pnl_pct": -5.7768,
      "reason": "TIME MAX",
      "bars": 15,
      "entry_bar": 646,
      "exit_bar": 661,
      "size": 583.2832,
      "equity_after": 549.5884
    },
    {
      "pair": "GUN/USD",
      "entry": 0.02609,
      "exit": 0.02807,
      "pnl": 42.4732,
      "pnl_pct": 7.0494,
      "reason": "RSI RECOVERY",
      "bars": 4,
      "entry_bar": 658,
      "exit_bar": 662,
      "size": 602.5095,
      "equity_after": 644.9827
    },
    {
      "pair": "PLAY/USD",
      "entry": 0.097463,
      "exit": 0.101681,
      "pnl": 20.8654,
      "pnl_pct": 3.7965,
      "reason": "RSI RECOVERY",
      "bars": 3,
      "entry_bar": 661,
      "exit_bar": 664,
      "size": 549.5884,
      "equity_after": 570.4538
    },
    {
      "pair": "EPT/USD",
      "entry": 0.000831,
      "exit": 0.000739,
      "pnl": -80.8628,
      "pnl_pct": -11.5622,
      "reason": "TIME MAX",
      "bars": 15,
      "entry_bar": 650,
      "exit_bar": 665,
      "size": 699.3714,
      "equity_after": 618.5086
    },
    {
      "pair": "AVAAI/USD",
      "entry": 0.0077,
      "exit": 0.00817,
      "pnl": 34.4387,
      "pnl_pct": 5.568,
      "reason": "RSI RECOVERY",
      "bars": 3,
      "entry_bar": 665,
      "exit_bar": 668,
      "size": 618.5086,
      "equity_after": 652.9473
    },
    {
      "pair": "BABY/USD",
      "entry": 0.01498,
      "exit": 0.012733,
      "pnl": -99.8498,
      "pnl_pct": -15.481,
      "reason": "FIXED STOP",
      "bars": 10,
      "entry_bar": 662,
      "exit_bar": 672,
      "size": 644.9827,
      "equity_after": 545.1329
    },
    {
      "pair": "LINEA/USD",
      "entry": 0.00401,
      "exit": 0.0034085,
      "pnl": -88.3119,
      "pnl_pct": -15.481,
      "reason": "FIXED STOP",
      "bars": 8,
      "entry_bar": 664,
      "exit_bar": 672,
      "size": 570.4538,
      "equity_after": 1027.2747
    },
    {
      "pair": "CHILLHOUSE/USD",
      "entry": 0.00213,
      "exit": 0.0018105,
      "pnl": -101.0828,
      "pnl_pct": -15.481,
      "reason": "FIXED STOP",
      "bars": 5,
      "entry_bar": 668,
      "exit_bar": 673,
      "size": 652.9473,
      "equity_after": 551.8646
    },
    {
      "pair": "1INCH/USD",
      "entry": 0.0975,
      "exit": 0.082875,
      "pnl": -79.5162,
      "pnl_pct": -15.481,
      "reason": "FIXED STOP",
      "bars": 3,
      "entry_bar": 672,
      "exit_bar": 675,
      "size": 513.6374,
      "equity_after": 434.1212
    },
    {
      "pair": "AIXBT/USD",
      "entry": 0.02227,
      "exit": 0.0189295,
      "pnl": -79.5162,
      "pnl_pct": -15.481,
      "reason": "FIXED STOP",
      "bars": 3,
      "entry_bar": 672,
      "exit_bar": 675,
      "size": 513.6374,
      "equity_after": 868.2423
    },
    {
      "pair": "TON/USD",
      "entry": 1.241,
      "exit": 1.294,
      "pnl": 16.2346,
      "pnl_pct": 3.7396,
      "reason": "DC TARGET",
      "bars": 2,
      "entry_bar": 675,
      "exit_bar": 677,
      "size": 434.1212,
      "equity_after": 450.3557
    },
    {
      "pair": "AEVO/USD",
      "entry": 0.02805,
      "exit": 0.03007,
      "pnl": 28.9242,
      "pnl_pct": 6.6627,
      "reason": "RSI RECOVERY",
      "bars": 3,
      "entry_bar": 675,
      "exit_bar": 678,
      "size": 434.1212,
      "equity_after": 463.0454
    },
    {
      "pair": "ANKR/USD",
      "entry": 0.00462,
      "exit": 0.00475,
      "pnl": 12.6186,
      "pnl_pct": 2.2865,
      "reason": "DC TARGET",
      "bars": 12,
      "entry_bar": 673,
      "exit_bar": 685,
      "size": 551.8646,
      "equity_after": 564.4832
    },
    {
      "pair": "WMTX/USD",
      "entry": 0.0737,
      "exit": 0.0766,
      "pnl": 15.333,
      "pnl_pct": 3.4046,
      "reason": "RSI RECOVERY",
      "bars": 9,
      "entry_bar": 677,
      "exit_bar": 686,
      "size": 450.3557,
      "equity_after": 465.6887
    },
    {
      "pair": "ARC/USD",
      "entry": 0.05599,
      "exit": 0.072,
      "pnl": 158.0555,
      "pnl_pct": 28.0,
      "reason": "RSI RECOVERY",
      "bars": 2,
      "entry_bar": 685,
      "exit_bar": 687,
      "size": 564.4832,
      "equity_after": 722.5387
    },
    {
      "pair": "MIR/USD",
      "entry": 0.00433,
      "exit": 0.00433,
      "pnl": -2.4078,
      "pnl_pct": -0.52,
      "reason": "TIME MAX",
      "bars": 15,
      "entry_bar": 678,
      "exit_bar": 693,
      "size": 463.0454,
      "equity_after": 460.6375
    },
    {
      "pair": "MAT/USD",
      "entry": 0.0764,
      "exit": 0.0776,
      "pnl": 4.8739,
      "pnl_pct": 1.0466,
      "reason": "RSI RECOVERY",
      "bars": 13,
      "entry_bar": 686,
      "exit_bar": 699,
      "size": 465.6887,
      "equity_after": 470.5626
    },
    {
      "pair": "C98/USD",
      "entry": 0.02762,
      "exit": 0.02652,
      "pnl": -32.4584,
      "pnl_pct": -4.4923,
      "reason": "TIME MAX",
      "bars": 15,
      "entry_bar": 687,
      "exit_bar": 702,
      "size": 722.5387,
      "equity_after": 690.0803
    },
    {
      "pair": "ICX/USD",
      "entry": 0.03908,
      "exit": 0.03971,
      "pnl": 5.1192,
      "pnl_pct": 1.0879,
      "reason": "RSI RECOVERY",
      "bars": 3,
      "entry_bar": 699,
      "exit_bar": 702,
      "size": 470.5626,
      "equity_after": 1165.7621
    },
    {
      "pair": "AI3/USD",
      "entry": 0.01273,
      "exit": 0.01243,
      "pnl": -13.2226,
      "pnl_pct": -2.8705,
      "reason": "RSI RECOVERY",
      "bars": 11,
      "entry_bar": 693,
      "exit_bar": 704,
      "size": 460.6375,
      "equity_after": 447.4149
    },
    {
      "pair": "ENJ/USD",
      "entry": 0.0221,
      "exit": 0.02247,
      "pnl": 6.7023,
      "pnl_pct": 1.1499,
      "reason": "RSI RECOVERY",
      "bars": 3,
      "entry_bar": 702,
      "exit_bar": 705,
      "size": 582.8811,
      "equity_after": 589.5834
    },
    {
      "pair": "MYX/USD",
      "entry": 5.871,
      "exit": 4.99035,
      "pnl": -90.2358,
      "pnl_pct": -15.481,
      "reason": "FIXED STOP",
      "bars": 4,
      "entry_bar": 702,
      "exit_bar": 706,
      "size": 582.8811,
      "equity_after": 492.6453
    },
    {
      "pair": "ANKR/USD",
      "entry": 0.00428,
      "exit": 0.00441,
      "pnl": 12.3629,
      "pnl_pct": 2.5095,
      "reason": "RSI RECOVERY",
      "bars": 3,
      "entry_bar": 706,
      "exit_bar": 709,
      "size": 492.6453,
      "equity_after": 505.0081
    },
    {
      "pair": "UNFI/USD",
      "entry": 0.0781,
      "exit": 0.0836,
      "pnl": 38.3462,
      "pnl_pct": 6.5039,
      "reason": "RSI RECOVERY",
      "bars": 8,
      "entry_bar": 705,
      "exit_bar": 713,
      "size": 589.5834,
      "equity_after": 627.9295
    },
    {
      "pair": "ALKIMI/USD",
      "entry": 0.0096,
      "exit": 0.0101,
      "pnl": 23.6081,
      "pnl_pct": 4.6748,
      "reason": "RSI RECOVERY",
      "bars": 6,
      "entry_bar": 709,
      "exit_bar": 715,
      "size": 505.0081,
      "equity_after": 528.6162
    },
    {
      "pair": "STEP/USD",
      "entry": 0.00113,
      "exit": 0.00116,
      "pnl": 13.3621,
      "pnl_pct": 2.128,
      "reason": "RSI RECOVERY",
      "bars": 3,
      "entry_bar": 713,
      "exit_bar": 716,
      "size": 627.9295,
      "equity_after": 641.2916
    },
    {
      "pair": "XMN/USD",
      "entry": 0.01358,
      "exit": 0.01351,
      "pnl": -4.6268,
      "pnl_pct": -1.0341,
      "reason": "RSI RECOVERY",
      "bars": 13,
      "entry_bar": 704,
      "exit_bar": 717,
      "size": 447.4149,
      "equity_after": 442.788
    },
    {
      "pair": "DBR/USD",
      "entry": 0.0155,
      "exit": 0.01584,
      "pnl": 8.8165,
      "pnl_pct": 1.6678,
      "reason": "END",
      "bars": 5,
      "entry_bar": 715,
      "exit_bar": 720,
      "size": 528.6162,
      "equity_after": 537.4327
    },
    {
      "pair": "PLAY/USD",
      "entry": 0.05315,
      "exit": 0.054287,
      "pnl": 10.3483,
      "pnl_pct": 1.6137,
      "reason": "END",
      "bars": 4,
      "entry_bar": 716,
      "exit_bar": 720,
      "size": 641.2916,
      "equity_after": 1189.0727
    },
    {
      "pair": "LCX/USD",
      "entry": 0.04762,
      "exit": 0.04793,
      "pnl": 0.5725,
      "pnl_pct": 0.1293,
      "reason": "END",
      "bars": 3,
      "entry_bar": 717,
      "exit_bar": 720,
      "size": 442.788,
      "equity_after": 1632.4332
    }
  ]
}